[
 {
  "start": 1.2,
  "end": 1.7,
  "who": 3
 },
 {
  "start": 2.7,
  "end": 3.2,
  "who": 3
 },
 {
  "start": 5.7,
  "end": 6.2,
  "who": 3
 },
 {
  "start": 6.7,
  "end": 7.2,
  "who": 4
 },
 {
  "start": 7.2,
  "end": 9.2,
  "who": 1
 },
 {
  "start": 9.33,
  "end": 11.83,
  "who": 1
 },
 {
  "start": 12.33,
  "end": 17.33,
  "who": 1
 },
 {
  "start": 17.46,
  "end": 23.46,
  "who": 1
 },
 {
  "start": 23.46,
  "end": 23.96,
  "who": 0
 },
 {
  "start": 23.96,
  "end": 24.09,
  "who": 2
 },
 {
  "start": 24.45,
  "end": 24.95,
  "who": 4
 },
 {
  "start": 24.95,
  "end": 26.45,
  "who": 1
 },
 {
  "start": 26.45,
  "end": 26.95,
  "who": 4
 },
 {
  "start": 26.95,
  "end": 28.45,
  "who": 1
 },
 {
  "start": 28.45,
  "end": 28.95,
  "who": 0
 },
 {
  "start": 28.95,
  "end": 29.95,
  "who": 1
 },
 {
  "start": 29.95,
  "end": 32.45,
  "who": 0
 },
 {
  "start": 32.58,
  "end": 34.58,
  "who": 0
 },
 {
  "start": 34.74,
  "end": 43.71,
  "who": 0
 },
 {
  "start": 44.07,
  "end": 48.81,
  "who": 0
 },
 {
  "start": 48.93,
  "end": 49.43,
  "who": 1
 },
 {
  "start": 49.43,
  "end": 50.93,
  "who": 0
 },
 {
  "start": 51.33,
  "end": 51.83,
  "who": 2
 },
 {
  "start": 51.83,
  "end": 53.33,
  "who": 1
 },
 {
  "start": 53.83,
  "end": 54.83,
  "who": 0
 },
 {
  "start": 54.83,
  "end": 55.33,
  "who": 1
 },
 {
  "start": 55.33,
  "end": 56.33,
  "who": 0
 },
 {
  "start": 57.6,
  "end": 59.6,
  "who": 0
 },
 {
  "start": 59.6,
  "end": 60.6,
  "who": 1
 },
 {
  "start": 60.6,
  "end": 61.1,
  "who": 0
 },
 {
  "start": 61.1,
  "end": 64.6,
  "who": 1
 },
 {
  "start": 64.6,
  "end": 65.6,
  "who": 0
 },
 {
  "start": 65.73,
  "end": 66.73,
  "who": 0
 },
 {
  "start": 66.73,
  "end": 67.23,
  "who": 1
 },
 {
  "start": 67.23,
  "end": 73.73,
  "who": 0
 },
 {
  "start": 73.86,
  "end": 79.36,
  "who": 0
 },
 {
  "start": 79.36,
  "end": 79.86,
  "who": 2
 },
 {
  "start": 79.86,
  "end": 81.86,
  "who": 0
 },
 {
  "start": 81.99,
  "end": 86.49,
  "who": 0
 },
 {
  "start": 86.79,
  "end": 88.79,
  "who": 1
 },
 {
  "start": 88.79,
  "end": 89.29,
  "who": 0
 },
 {
  "start": 89.29,
  "end": 90.79,
  "who": 1
 },
 {
  "start": 91.61,
  "end": 93.61,
  "who": 1
 },
 {
  "start": 93.61,
  "end": 94.61,
  "who": 0
 },
 {
  "start": 94.61,
  "end": 95.11,
  "who": 2
 },
 {
  "start": 95.11,
  "end": 96.11,
  "who": 0
 },
 {
  "start": 96.42,
  "end": 97.42,
  "who": 0
 },
 {
  "start": 97.92,
  "end": 102.63,
  "who": 0
 },
 {
  "start": 103.14,
  "end": 103.64,
  "who": 0
 },
 {
  "start": 103.64,
  "end": 104.14,
  "who": 3
 },
 {
  "start": 104.14,
  "end": 106.41,
  "who": 0
 },
 {
  "start": 106.77,
  "end": 107.58,
  "who": 0
 },
 {
  "start": 107.79,
  "end": 109.79,
  "who": 0
 },
 {
  "start": 110.29,
  "end": 115.79,
  "who": 0
 },
 {
  "start": 115.92,
  "end": 118.42,
  "who": 0
 },
 {
  "start": 118.92,
  "end": 119.42,
  "who": 3
 },
 {
  "start": 120.72,
  "end": 122.22,
  "who": 0
 },
 {
  "start": 122.73,
  "end": 124.73,
  "who": 1
 },
 {
  "start": 124.73,
  "end": 130.23000000000002,
  "who": 0
 },
 {
  "start": 130.23000000000002,
  "end": 130.73000000000002,
  "who": 2
 },
 {
  "start": 130.86,
  "end": 131.36,
  "who": 1
 },
 {
  "start": 131.36,
  "end": 132.36,
  "who": 0
 },
 {
  "start": 133.02,
  "end": 135.02,
  "who": 0
 },
 {
  "start": 135.75,
  "end": 142.25,
  "who": 0
 },
 {
  "start": 142.5,
  "end": 146.0,
  "who": 0
 },
 {
  "start": 146.82,
  "end": 151.05,
  "who": 0
 },
 {
  "start": 152.01,
  "end": 160.47,
  "who": 0
 },
 {
  "start": 161.79,
  "end": 168.79,
  "who": 0
 },
 {
  "start": 169.23,
  "end": 169.73,
  "who": 0
 },
 {
  "start": 169.73,
  "end": 172.73,
  "who": 1
 },
 {
  "start": 172.73,
  "end": 173.23,
  "who": 0
 },
 {
  "start": 173.23,
  "end": 174.23,
  "who": 1
 },
 {
  "start": 174.23,
  "end": 183.36,
  "who": 0
 },
 {
  "start": 183.81,
  "end": 185.31,
  "who": 0
 },
 {
  "start": 185.61,
  "end": 190.11,
  "who": 0
 },
 {
  "start": 190.11,
  "end": 191.61,
  "who": 1
 },
 {
  "start": 191.61,
  "end": 192.11,
  "who": 3
 },
 {
  "start": 192.11,
  "end": 193.61,
  "who": 1
 },
 {
  "start": 193.74,
  "end": 199.24,
  "who": 0
 },
 {
  "start": 199.24,
  "end": 199.35,
  "who": 3
 },
 {
  "start": 199.92,
  "end": 204.92,
  "who": 0
 },
 {
  "start": 205.23,
  "end": 209.49,
  "who": 0
 },
 {
  "start": 209.61,
  "end": 211.11,
  "who": 0
 },
 {
  "start": 211.11,
  "end": 211.47,
  "who": 3
 },
 {
  "start": 211.92,
  "end": 213.42,
  "who": 0
 },
 {
  "start": 214.05,
  "end": 214.89,
  "who": 0
 },
 {
  "start": 215.25,
  "end": 215.61,
  "who": 2
 },
 {
  "start": 215.85,
  "end": 219.35,
  "who": 0
 },
 {
  "start": 219.35,
  "end": 219.85,
  "who": 1
 },
 {
  "start": 219.85,
  "end": 220.35,
  "who": 0
 },
 {
  "start": 220.35,
  "end": 221.35,
  "who": 1
 },
 {
  "start": 221.73,
  "end": 222.23,
  "who": 0
 },
 {
  "start": 222.23,
  "end": 222.73,
  "who": 2
 },
 {
  "start": 222.73,
  "end": 223.23,
  "who": 0
 },
 {
  "start": 223.23,
  "end": 223.73,
  "who": 1
 },
 {
  "start": 223.73,
  "end": 226.23,
  "who": 0
 },
 {
  "start": 226.23,
  "end": 227.23,
  "who": 1
 },
 {
  "start": 227.23,
  "end": 229.23,
  "who": 0
 },
 {
  "start": 229.23,
  "end": 229.5,
  "who": 2
 },
 {
  "start": 229.92,
  "end": 231.75,
  "who": 0
 },
 {
  "start": 232.11,
  "end": 237.06,
  "who": 0
 },
 {
  "start": 237.39,
  "end": 238.39,
  "who": 0
 },
 {
  "start": 238.39,
  "end": 238.56,
  "who": 2
 },
 {
  "start": 238.77,
  "end": 248.13,
  "who": 0
 },
 {
  "start": 248.34,
  "end": 248.84,
  "who": 1
 },
 {
  "start": 248.84,
  "end": 251.84,
  "who": 0
 },
 {
  "start": 251.84,
  "end": 252.78,
  "who": 1
 },
 {
  "start": 252.96,
  "end": 255.96,
  "who": 0
 },
 {
  "start": 255.96,
  "end": 256.46000000000004,
  "who": 1
 },
 {
  "start": 256.46000000000004,
  "end": 259.46000000000004,
  "who": 0
 },
 {
  "start": 261.33,
  "end": 261.63,
  "who": 3
 },
 {
  "start": 264.39,
  "end": 265.39,
  "who": 0
 },
 {
  "start": 265.39,
  "end": 265.59,
  "who": 4
 },
 {
  "start": 265.86,
  "end": 266.36,
  "who": 0
 },
 {
  "start": 266.36,
  "end": 270.86,
  "who": 1
 },
 {
  "start": 270.86,
  "end": 271.86,
  "who": 0
 },
 {
  "start": 271.86,
  "end": 272.36,
  "who": 1
 },
 {
  "start": 272.36,
  "end": 273.36,
  "who": 0
 },
 {
  "start": 276.84,
  "end": 278.13,
  "who": 0
 },
 {
  "start": 278.85,
  "end": 281.85,
  "who": 1
 },
 {
  "start": 281.85,
  "end": 282.35,
  "who": 4
 },
 {
  "start": 282.35,
  "end": 283.85,
  "who": 1
 },
 {
  "start": 283.85,
  "end": 286.85,
  "who": 0
 },
 {
  "start": 286.98,
  "end": 289.98,
  "who": 0
 },
 {
  "start": 289.98,
  "end": 290.43,
  "who": 1
 },
 {
  "start": 290.7,
  "end": 291.2,
  "who": 0
 },
 {
  "start": 291.2,
  "end": 291.45,
  "who": 4
 },
 {
  "start": 292.02,
  "end": 296.02,
  "who": 0
 },
 {
  "start": 296.02,
  "end": 296.19,
  "who": 2
 },
 {
  "start": 296.4,
  "end": 301.86,
  "who": 0
 },
 {
  "start": 302.88,
  "end": 303.88,
  "who": 1
 },
 {
  "start": 303.88,
  "end": 304.35,
  "who": 0
 },
 {
  "start": 304.56,
  "end": 305.06,
  "who": 0
 },
 {
  "start": 305.06,
  "end": 305.31,
  "who": 4
 },
 {
  "start": 305.76,
  "end": 309.76,
  "who": 0
 },
 {
  "start": 312.6,
  "end": 313.1,
  "who": 2
 },
 {
  "start": 313.1,
  "end": 316.1,
  "who": 1
 },
 {
  "start": 316.6,
  "end": 318.6,
  "who": 1
 },
 {
  "start": 318.6,
  "end": 319.1,
  "who": 4
 },
 {
  "start": 319.1,
  "end": 320.6,
  "who": 1
 },
 {
  "start": 320.73,
  "end": 321.23,
  "who": 0
 },
 {
  "start": 321.23,
  "end": 323.23,
  "who": 1
 },
 {
  "start": 323.23,
  "end": 323.73,
  "who": 4
 },
 {
  "start": 323.73,
  "end": 326.3,
  "who": 1
 },
 {
  "start": 326.3,
  "end": 332.3,
  "who": 0
 },
 {
  "start": 332.43,
  "end": 335.93,
  "who": 0
 },
 {
  "start": 335.93,
  "end": 336.12,
  "who": 3
 },
 {
  "start": 336.51,
  "end": 340.89,
  "who": 0
 },
 {
  "start": 341.1,
  "end": 341.6,
  "who": 3
 },
 {
  "start": 341.6,
  "end": 342.1,
  "who": 4
 },
 {
  "start": 342.1,
  "end": 345.1,
  "who": 0
 },
 {
  "start": 345.1,
  "end": 346.44,
  "who": 1
 },
 {
  "start": 346.68,
  "end": 347.68,
  "who": 0
 },
 {
  "start": 347.68,
  "end": 348.18,
  "who": 1
 },
 {
  "start": 348.18,
  "end": 359.46,
  "who": 0
 },
 {
  "start": 360.15,
  "end": 361.11,
  "who": 0
 },
 {
  "start": 361.35,
  "end": 364.35,
  "who": 0
 },
 {
  "start": 364.83,
  "end": 368.83,
  "who": 0
 },
 {
  "start": 368.97,
  "end": 369.9,
  "who": 0
 },
 {
  "start": 370.2,
  "end": 370.41,
  "who": 3
 },
 {
  "start": 370.68,
  "end": 371.18,
  "who": 1
 },
 {
  "start": 371.18,
  "end": 371.68,
  "who": 3
 },
 {
  "start": 371.68,
  "end": 375.18,
  "who": 1
 },
 {
  "start": 375.18,
  "end": 376.18,
  "who": 0
 },
 {
  "start": 376.18,
  "end": 378.68,
  "who": 1
 },
 {
  "start": 378.81,
  "end": 381.81,
  "who": 1
 },
 {
  "start": 381.81,
  "end": 382.31,
  "who": 0
 },
 {
  "start": 382.31,
  "end": 383.81,
  "who": 1
 },
 {
  "start": 383.81,
  "end": 384.31,
  "who": 2
 },
 {
  "start": 384.31,
  "end": 390.94,
  "who": 0
 },
 {
  "start": 390.94,
  "end": 391.26,
  "who": 4
 },
 {
  "start": 392.28,
  "end": 392.78,
  "who": 1
 },
 {
  "start": 392.78,
  "end": 392.97,
  "who": 4
 },
 {
  "start": 393.33,
  "end": 394.33,
  "who": 1
 },
 {
  "start": 394.33,
  "end": 399.81,
  "who": 0
 },
 {
  "start": 399.99,
  "end": 401.49,
  "who": 0
 },
 {
  "start": 402.54,
  "end": 410.04,
  "who": 1
 },
 {
  "start": 410.04,
  "end": 410.54,
  "who": 4
 },
 {
  "start": 410.73,
  "end": 415.73,
  "who": 1
 },
 {
  "start": 416.23,
  "end": 417.23,
  "who": 1
 },
 {
  "start": 417.23,
  "end": 417.73,
  "who": 2
 },
 {
  "start": 417.73,
  "end": 418.73,
  "who": 1
 },
 {
  "start": 418.86,
  "end": 419.86,
  "who": 1
 },
 {
  "start": 420.63,
  "end": 421.13,
  "who": 2
 },
 {
  "start": 421.13,
  "end": 424.63,
  "who": 1
 },
 {
  "start": 425.37,
  "end": 426.87,
  "who": 2
 },
 {
  "start": 426.87,
  "end": 427.37,
  "who": 0
 },
 {
  "start": 427.37,
  "end": 429.87,
  "who": 2
 },
 {
  "start": 429.87,
  "end": 430.37,
  "who": 3
 },
 {
  "start": 430.37,
  "end": 433.37,
  "who": 2
 },
 {
  "start": 433.5,
  "end": 446.13,
  "who": 2
 },
 {
  "start": 446.13,
  "end": 446.52,
  "who": 0
 },
 {
  "start": 446.58,
  "end": 450.08,
  "who": 2
 },
 {
  "start": 451.65,
  "end": 451.86,
  "who": 3
 },
 {
  "start": 453.69,
  "end": 454.19,
  "who": 0
 },
 {
  "start": 454.19,
  "end": 455.19,
  "who": 3
 },
 {
  "start": 455.19,
  "end": 455.69,
  "who": 1
 },
 {
  "start": 455.69,
  "end": 456.19,
  "who": 3
 },
 {
  "start": 456.19,
  "end": 456.69,
  "who": 2
 },
 {
  "start": 456.69,
  "end": 457.19,
  "who": 0
 },
 {
  "start": 457.19,
  "end": 458.69,
  "who": 3
 },
 {
  "start": 458.69,
  "end": 459.19,
  "who": 2
 },
 {
  "start": 459.19,
  "end": 459.69,
  "who": 1
 },
 {
  "start": 459.69,
  "end": 460.19,
  "who": 4
 },
 {
  "start": 460.19,
  "end": 460.29,
  "who": 0
 },
 {
  "start": 460.32,
  "end": 460.82,
  "who": 1
 },
 {
  "start": 460.82,
  "end": 461.82,
  "who": 4
 },
 {
  "start": 461.82,
  "end": 462.32,
  "who": 3
 },
 {
  "start": 463.32,
  "end": 463.82,
  "who": 1
 },
 {
  "start": 464.32,
  "end": 465.82,
  "who": 3
 },
 {
  "start": 465.82,
  "end": 466.32,
  "who": 1
 },
 {
  "start": 466.32,
  "end": 476.45,
  "who": 3
 },
 {
  "start": 476.58,
  "end": 478.58,
  "who": 3
 },
 {
  "start": 478.58,
  "end": 478.89,
  "who": 1
 },
 {
  "start": 479.01,
  "end": 484.01,
  "who": 3
 },
 {
  "start": 484.51,
  "end": 489.9,
  "who": 3
 },
 {
  "start": 490.02,
  "end": 490.52,
  "who": 3
 },
 {
  "start": 490.52,
  "end": 491.02,
  "who": 1
 },
 {
  "start": 491.02,
  "end": 491.52,
  "who": 3
 },
 {
  "start": 492.02,
  "end": 492.52,
  "who": 4
 },
 {
  "start": 492.52,
  "end": 493.02,
  "who": 1
 },
 {
  "start": 493.02,
  "end": 493.52,
  "who": 3
 },
 {
  "start": 493.52,
  "end": 494.02,
  "who": 0
 },
 {
  "start": 494.02,
  "end": 494.52,
  "who": 3
 },
 {
  "start": 494.52,
  "end": 495.02,
  "who": 0
 },
 {
  "start": 495.02,
  "end": 495.52,
  "who": 2
 },
 {
  "start": 495.52,
  "end": 496.02,
  "who": 1
 },
 {
  "start": 496.02,
  "end": 496.52,
  "who": 2
 },
 {
  "start": 496.52,
  "end": 497.01,
  "who": 1
 },
 {
  "start": 497.1,
  "end": 498.6,
  "who": 3
 },
 {
  "start": 498.6,
  "end": 499.1,
  "who": 1
 },
 {
  "start": 499.1,
  "end": 500.6,
  "who": 3
 },
 {
  "start": 500.6,
  "end": 501.1,
  "who": 1
 },
 {
  "start": 501.1,
  "end": 505.1,
  "who": 3
 },
 {
  "start": 505.23,
  "end": 509.73,
  "who": 3
 },
 {
  "start": 510.23,
  "end": 513.33,
  "who": 3
 },
 {
  "start": 513.36,
  "end": 513.86,
  "who": 1
 },
 {
  "start": 513.86,
  "end": 514.36,
  "who": 3
 },
 {
  "start": 514.36,
  "end": 514.86,
  "who": 1
 },
 {
  "start": 514.86,
  "end": 515.36,
  "who": 3
 },
 {
  "start": 515.36,
  "end": 515.86,
  "who": 1
 },
 {
  "start": 516.36,
  "end": 516.86,
  "who": 4
 },
 {
  "start": 516.86,
  "end": 517.36,
  "who": 3
 },
 {
  "start": 517.36,
  "end": 517.86,
  "who": 0
 },
 {
  "start": 517.86,
  "end": 518.36,
  "who": 4
 },
 {
  "start": 518.36,
  "end": 518.86,
  "who": 3
 },
 {
  "start": 519.86,
  "end": 520.36,
  "who": 1
 },
 {
  "start": 520.36,
  "end": 520.86,
  "who": 2
 },
 {
  "start": 520.86,
  "end": 521.36,
  "who": 4
 },
 {
  "start": 521.49,
  "end": 522.49,
  "who": 1
 },
 {
  "start": 522.49,
  "end": 522.99,
  "who": 3
 },
 {
  "start": 522.99,
  "end": 523.99,
  "who": 1
 },
 {
  "start": 523.99,
  "end": 524.49,
  "who": 3
 },
 {
  "start": 524.49,
  "end": 524.99,
  "who": 0
 },
 {
  "start": 524.99,
  "end": 525.99,
  "who": 1
 },
 {
  "start": 525.99,
  "end": 526.49,
  "who": 4
 },
 {
  "start": 526.49,
  "end": 526.99,
  "who": 2
 },
 {
  "start": 526.99,
  "end": 527.49,
  "who": 3
 },
 {
  "start": 527.49,
  "end": 527.99,
  "who": 1
 },
 {
  "start": 528.21,
  "end": 536.21,
  "who": 4
 },
 {
  "start": 536.4,
  "end": 540.9,
  "who": 4
 },
 {
  "start": 541.44,
  "end": 547.94,
  "who": 4
 },
 {
  "start": 548.16,
  "end": 550.32,
  "who": 3
 },
 {
  "start": 550.47,
  "end": 550.97,
  "who": 1
 },
 {
  "start": 550.97,
  "end": 551.47,
  "who": 3
 },
 {
  "start": 551.47,
  "end": 560.6,
  "who": 4
 },
 {
  "start": 560.6,
  "end": 561.6,
  "who": 3
 },
 {
  "start": 561.6,
  "end": 562.6,
  "who": 0
 },
 {
  "start": 563.1,
  "end": 563.6,
  "who": 2
 },
 {
  "start": 563.6,
  "end": 564.1,
  "who": 3
 },
 {
  "start": 564.1,
  "end": 565.1,
  "who": 1
 },
 {
  "start": 565.1,
  "end": 565.6,
  "who": 2
 },
 {
  "start": 565.6,
  "end": 565.98,
  "who": 0
 },
 {
  "start": 566.01,
  "end": 566.51,
  "who": 3
 },
 {
  "start": 567.01,
  "end": 567.51,
  "who": 2
 },
 {
  "start": 567.51,
  "end": 569.51,
  "who": 3
 },
 {
  "start": 569.51,
  "end": 572.43,
  "who": 4
 },
 {
  "start": 572.64,
  "end": 577.14,
  "who": 4
 },
 {
  "start": 577.14,
  "end": 577.38,
  "who": 2
 },
 {
  "start": 577.86,
  "end": 580.36,
  "who": 4
 },
 {
  "start": 580.68,
  "end": 581.64,
  "who": 4
 },
 {
  "start": 581.88,
  "end": 585.88,
  "who": 4
 },
 {
  "start": 586.26,
  "end": 587.26,
  "who": 4
 },
 {
  "start": 587.26,
  "end": 587.76,
  "who": 1
 },
 {
  "start": 587.76,
  "end": 588.76,
  "who": 4
 },
 {
  "start": 588.76,
  "end": 589.26,
  "who": 3
 },
 {
  "start": 589.65,
  "end": 594.39,
  "who": 4
 },
 {
  "start": 595.02,
  "end": 596.79,
  "who": 4
 },
 {
  "start": 597.0,
  "end": 599.46,
  "who": 4
 },
 {
  "start": 599.73,
  "end": 600.23,
  "who": 4
 },
 {
  "start": 600.73,
  "end": 602.73,
  "who": 4
 },
 {
  "start": 602.73,
  "end": 603.73,
  "who": 3
 },
 {
  "start": 603.73,
  "end": 605.23,
  "who": 1
 },
 {
  "start": 605.23,
  "end": 605.73,
  "who": 3
 },
 {
  "start": 605.73,
  "end": 606.73,
  "who": 2
 },
 {
  "start": 606.73,
  "end": 607.23,
  "who": 0
 },
 {
  "start": 607.23,
  "end": 607.73,
  "who": 1
 },
 {
  "start": 607.89,
  "end": 608.39,
  "who": 1
 },
 {
  "start": 608.39,
  "end": 608.89,
  "who": 4
 },
 {
  "start": 608.89,
  "end": 609.39,
  "who": 0
 },
 {
  "start": 609.39,
  "end": 609.89,
  "who": 2
 },
 {
  "start": 609.89,
  "end": 610.39,
  "who": 3
 },
 {
  "start": 610.39,
  "end": 615.89,
  "who": 4
 },
 {
  "start": 615.89,
  "end": 615.99,
  "who": 2
 },
 {
  "start": 616.02,
  "end": 619.52,
  "who": 4
 },
 {
  "start": 619.52,
  "end": 620.02,
  "who": 1
 },
 {
  "start": 620.02,
  "end": 620.13,
  "who": 3
 },
 {
  "start": 620.31,
  "end": 621.81,
  "who": 4
 },
 {
  "start": 622.31,
  "end": 624.81,
  "who": 4
 },
 {
  "start": 625.31,
  "end": 627.48,
  "who": 4
 },
 {
  "start": 627.6,
  "end": 629.6,
  "who": 4
 },
 {
  "start": 630.12,
  "end": 635.61,
  "who": 4
 },
 {
  "start": 636.18,
  "end": 636.68,
  "who": 3
 },
 {
  "start": 637.18,
  "end": 638.18,
  "who": 3
 },
 {
  "start": 638.18,
  "end": 638.68,
  "who": 1
 },
 {
  "start": 638.68,
  "end": 639.68,
  "who": 3
 },
 {
  "start": 639.68,
  "end": 640.68,
  "who": 4
 },
 {
  "start": 640.68,
  "end": 641.18,
  "who": 3
 },
 {
  "start": 641.18,
  "end": 642.18,
  "who": 4
 },
 {
  "start": 642.18,
  "end": 643.18,
  "who": 3
 },
 {
  "start": 643.18,
  "end": 643.68,
  "who": 2
 },
 {
  "start": 643.68,
  "end": 644.18,
  "who": 3
 },
 {
  "start": 644.31,
  "end": 645.31,
  "who": 3
 },
 {
  "start": 645.81,
  "end": 646.31,
  "who": 2
 },
 {
  "start": 646.31,
  "end": 647.31,
  "who": 3
 },
 {
  "start": 647.31,
  "end": 647.81,
  "who": 2
 },
 {
  "start": 647.81,
  "end": 648.31,
  "who": 1
 },
 {
  "start": 648.31,
  "end": 648.81,
  "who": 3
 },
 {
  "start": 648.81,
  "end": 649.31,
  "who": 4
 },
 {
  "start": 649.81,
  "end": 650.81,
  "who": 4
 },
 {
  "start": 650.81,
  "end": 651.31,
  "who": 3
 },
 {
  "start": 651.87,
  "end": 652.37,
  "who": 4
 },
 {
  "start": 652.37,
  "end": 653.37,
  "who": 3
 },
 {
  "start": 653.37,
  "end": 657.87,
  "who": 4
 },
 {
  "start": 657.87,
  "end": 658.37,
  "who": 3
 },
 {
  "start": 658.37,
  "end": 661.0,
  "who": 4
 },
 {
  "start": 662.0,
  "end": 662.5,
  "who": 1
 },
 {
  "start": 662.5,
  "end": 663.0,
  "who": 0
 },
 {
  "start": 663.0,
  "end": 664.5,
  "who": 4
 },
 {
  "start": 664.5,
  "end": 665.0,
  "who": 0
 },
 {
  "start": 665.66,
  "end": 666.16,
  "who": 4
 },
 {
  "start": 666.16,
  "end": 666.66,
  "who": 1
 },
 {
  "start": 666.66,
  "end": 667.5,
  "who": 4
 },
 {
  "start": 668.58,
  "end": 669.58,
  "who": 4
 },
 {
  "start": 670.98,
  "end": 671.48,
  "who": 1
 },
 {
  "start": 671.48,
  "end": 671.98,
  "who": 4
 },
 {
  "start": 673.08,
  "end": 674.52,
  "who": 4
 },
 {
  "start": 675.48,
  "end": 676.48,
  "who": 4
 },
 {
  "start": 678.06,
  "end": 678.56,
  "who": 0
 },
 {
  "start": 679.06,
  "end": 679.56,
  "who": 2
 },
 {
  "start": 679.56,
  "end": 679.71,
  "who": 4
 },
 {
  "start": 680.42,
  "end": 682.92,
  "who": 4
 },
 {
  "start": 684.18,
  "end": 684.68,
  "who": 4
 },
 {
  "start": 684.68,
  "end": 685.18,
  "who": 2
 },
 {
  "start": 685.18,
  "end": 685.68,
  "who": 0
 },
 {
  "start": 685.68,
  "end": 686.18,
  "who": 3
 },
 {
  "start": 686.18,
  "end": 687.18,
  "who": 4
 },
 {
  "start": 687.18,
  "end": 687.68,
  "who": 1
 },
 {
  "start": 688.18,
  "end": 688.59,
  "who": 4
 },
 {
  "start": 688.74,
  "end": 689.24,
  "who": 2
 },
 {
  "start": 689.24,
  "end": 690.12,
  "who": 4
 },
 {
  "start": 690.87,
  "end": 691.37,
  "who": 4
 },
 {
  "start": 691.37,
  "end": 691.87,
  "who": 0
 },
 {
  "start": 691.87,
  "end": 692.37,
  "who": 1
 },
 {
  "start": 692.37,
  "end": 693.12,
  "who": 4
 },
 {
  "start": 694.25,
  "end": 695.75,
  "who": 4
 },
 {
  "start": 696.25,
  "end": 697.25,
  "who": 2
 },
 {
  "start": 697.74,
  "end": 698.24,
  "who": 3
 },
 {
  "start": 698.74,
  "end": 699.24,
  "who": 3
 },
 {
  "start": 700.59,
  "end": 701.09,
  "who": 1
 },
 {
  "start": 701.09,
  "end": 701.59,
  "who": 3
 },
 {
  "start": 701.59,
  "end": 705.09,
  "who": 4
 },
 {
  "start": 705.09,
  "end": 705.59,
  "who": 2
 },
 {
  "start": 705.59,
  "end": 708.51,
  "who": 4
 },
 {
  "start": 708.66,
  "end": 709.66,
  "who": 4
 },
 {
  "start": 709.66,
  "end": 710.16,
  "who": 0
 },
 {
  "start": 710.64,
  "end": 712.14,
  "who": 4
 },
 {
  "start": 712.64,
  "end": 713.64,
  "who": 4
 },
 {
  "start": 713.64,
  "end": 714.14,
  "who": 1
 },
 {
  "start": 714.14,
  "end": 715.14,
  "who": 2
 },
 {
  "start": 715.14,
  "end": 717.14,
  "who": 4
 },
 {
  "start": 717.14,
  "end": 717.33,
  "who": 2
 },
 {
  "start": 717.6,
  "end": 719.6,
  "who": 4
 },
 {
  "start": 719.97,
  "end": 720.47,
  "who": 2
 },
 {
  "start": 720.47,
  "end": 725.47,
  "who": 4
 },
 {
  "start": 725.47,
  "end": 726.47,
  "who": 0
 },
 {
  "start": 726.47,
  "end": 726.97,
  "who": 3
 },
 {
  "start": 727.47,
  "end": 727.62,
  "who": 1
 },
 {
  "start": 727.74,
  "end": 728.7,
  "who": 3
 },
 {
  "start": 728.82,
  "end": 729.32,
  "who": 3
 },
 {
  "start": 729.32,
  "end": 729.82,
  "who": 2
 },
 {
  "start": 730.32,
  "end": 732.82,
  "who": 4
 },
 {
  "start": 733.32,
  "end": 735.78,
  "who": 4
 },
 {
  "start": 736.08,
  "end": 739.47,
  "who": 4
 },
 {
  "start": 739.68,
  "end": 742.56,
  "who": 4
 },
 {
  "start": 742.92,
  "end": 748.38,
  "who": 4
 },
 {
  "start": 748.53,
  "end": 749.53,
  "who": 4
 },
 {
  "start": 749.53,
  "end": 750.03,
  "who": 3
 },
 {
  "start": 750.03,
  "end": 750.51,
  "who": 4
 },
 {
  "start": 750.99,
  "end": 751.99,
  "who": 4
 },
 {
  "start": 751.99,
  "end": 752.99,
  "who": 3
 },
 {
  "start": 752.99,
  "end": 753.99,
  "who": 4
 },
 {
  "start": 755.25,
  "end": 755.75,
  "who": 4
 },
 {
  "start": 755.75,
  "end": 756.25,
  "who": 1
 },
 {
  "start": 756.25,
  "end": 757.23,
  "who": 4
 },
 {
  "start": 757.77,
  "end": 759.27,
  "who": 4
 },
 {
  "start": 759.27,
  "end": 759.77,
  "who": 1
 },
 {
  "start": 759.77,
  "end": 760.27,
  "who": 3
 },
 {
  "start": 760.27,
  "end": 760.77,
  "who": 1
 },
 {
  "start": 760.77,
  "end": 761.27,
  "who": 3
 },
 {
  "start": 761.27,
  "end": 761.77,
  "who": 0
 },
 {
  "start": 761.77,
  "end": 762.27,
  "who": 4
 },
 {
  "start": 762.27,
  "end": 762.6,
  "who": 0
 },
 {
  "start": 762.93,
  "end": 763.43,
  "who": 0
 },
 {
  "start": 763.43,
  "end": 764.43,
  "who": 3
 },
 {
  "start": 764.43,
  "end": 764.93,
  "who": 0
 },
 {
  "start": 764.93,
  "end": 765.43,
  "who": 1
 },
 {
  "start": 765.43,
  "end": 765.93,
  "who": 3
 },
 {
  "start": 765.93,
  "end": 766.43,
  "who": 2
 },
 {
  "start": 766.43,
  "end": 766.93,
  "who": 4
 },
 {
  "start": 767.46,
  "end": 767.96,
  "who": 1
 },
 {
  "start": 767.96,
  "end": 768.46,
  "who": 3
 },
 {
  "start": 768.46,
  "end": 769.46,
  "who": 1
 },
 {
  "start": 769.46,
  "end": 769.96,
  "who": 2
 },
 {
  "start": 769.96,
  "end": 773.46,
  "who": 4
 },
 {
  "start": 773.46,
  "end": 773.61,
  "who": 3
 },
 {
  "start": 773.82,
  "end": 775.23,
  "who": 4
 },
 {
  "start": 775.65,
  "end": 777.15,
  "who": 4
 },
 {
  "start": 777.65,
  "end": 783.15,
  "who": 4
 },
 {
  "start": 783.69,
  "end": 787.69,
  "who": 4
 },
 {
  "start": 788.16,
  "end": 789.16,
  "who": 4
 },
 {
  "start": 789.16,
  "end": 789.66,
  "who": 0
 },
 {
  "start": 789.66,
  "end": 792.03,
  "who": 4
 },
 {
  "start": 792.45,
  "end": 798.45,
  "who": 4
 },
 {
  "start": 798.51,
  "end": 799.01,
  "who": 2
 },
 {
  "start": 799.51,
  "end": 800.01,
  "who": 4
 },
 {
  "start": 800.01,
  "end": 800.51,
  "who": 3
 },
 {
  "start": 800.51,
  "end": 801.01,
  "who": 2
 },
 {
  "start": 801.01,
  "end": 801.51,
  "who": 1
 },
 {
  "start": 801.51,
  "end": 805.8,
  "who": 4
 },
 {
  "start": 806.07,
  "end": 807.07,
  "who": 4
 },
 {
  "start": 807.07,
  "end": 807.21,
  "who": 3
 },
 {
  "start": 807.51,
  "end": 811.01,
  "who": 4
 },
 {
  "start": 811.01,
  "end": 811.44,
  "who": 1
 },
 {
  "start": 811.86,
  "end": 814.68,
  "who": 4
 },
 {
  "start": 815.16,
  "end": 817.66,
  "who": 4
 },
 {
  "start": 818.16,
  "end": 820.66,
  "who": 4
 },
 {
  "start": 821.28,
  "end": 821.78,
  "who": 4
 },
 {
  "start": 821.78,
  "end": 822.28,
  "who": 2
 },
 {
  "start": 822.28,
  "end": 827.22,
  "who": 4
 },
 {
  "start": 827.4,
  "end": 828.12,
  "who": 4
 },
 {
  "start": 828.33,
  "end": 828.83,
  "who": 4
 },
 {
  "start": 828.83,
  "end": 828.96,
  "who": 0
 },
 {
  "start": 829.29,
  "end": 829.79,
  "who": 4
 },
 {
  "start": 829.79,
  "end": 830.29,
  "who": 1
 },
 {
  "start": 830.29,
  "end": 831.29,
  "who": 4
 },
 {
  "start": 831.81,
  "end": 832.81,
  "who": 1
 },
 {
  "start": 832.81,
  "end": 833.31,
  "who": 3
 },
 {
  "start": 833.31,
  "end": 833.81,
  "who": 1
 },
 {
  "start": 833.81,
  "end": 842.55,
  "who": 4
 },
 {
  "start": 843.53,
  "end": 844.5,
  "who": 4
 },
 {
  "start": 844.74,
  "end": 846.57,
  "who": 4
 },
 {
  "start": 847.02,
  "end": 849.02,
  "who": 4
 },
 {
  "start": 850.11,
  "end": 851.11,
  "who": 4
 },
 {
  "start": 852.11,
  "end": 852.61,
  "who": 2
 },
 {
  "start": 852.61,
  "end": 853.11,
  "who": 0
 },
 {
  "start": 853.11,
  "end": 853.61,
  "who": 3
 },
 {
  "start": 853.61,
  "end": 854.11,
  "who": 2
 },
 {
  "start": 854.11,
  "end": 855.11,
  "who": 3
 },
 {
  "start": 855.11,
  "end": 856.11,
  "who": 1
 },
 {
  "start": 856.11,
  "end": 856.61,
  "who": 2
 },
 {
  "start": 856.61,
  "end": 857.11,
  "who": 1
 },
 {
  "start": 857.11,
  "end": 857.49,
  "who": 3
 },
 {
  "start": 857.94,
  "end": 858.44,
  "who": 2
 },
 {
  "start": 858.44,
  "end": 858.94,
  "who": 0
 },
 {
  "start": 858.94,
  "end": 859.94,
  "who": 3
 },
 {
  "start": 859.94,
  "end": 860.44,
  "who": 4
 },
 {
  "start": 860.44,
  "end": 860.94,
  "who": 3
 },
 {
  "start": 860.94,
  "end": 861.44,
  "who": 1
 },
 {
  "start": 861.44,
  "end": 861.94,
  "who": 0
 },
 {
  "start": 861.94,
  "end": 862.44,
  "who": 3
 },
 {
  "start": 862.94,
  "end": 863.44,
  "who": 0
 },
 {
  "start": 863.44,
  "end": 863.94,
  "who": 3
 },
 {
  "start": 863.94,
  "end": 864.44,
  "who": 2
 },
 {
  "start": 864.44,
  "end": 864.94,
  "who": 0
 },
 {
  "start": 864.94,
  "end": 865.44,
  "who": 3
 },
 {
  "start": 865.44,
  "end": 865.94,
  "who": 1
 },
 {
  "start": 866.1,
  "end": 866.6,
  "who": 2
 },
 {
  "start": 866.6,
  "end": 867.6,
  "who": 3
 },
 {
  "start": 868.1,
  "end": 868.6,
  "who": 0
 },
 {
  "start": 868.6,
  "end": 869.1,
  "who": 4
 },
 {
  "start": 869.6,
  "end": 870.1,
  "who": 0
 },
 {
  "start": 870.1,
  "end": 871.1,
  "who": 4
 },
 {
  "start": 871.1,
  "end": 871.6,
  "who": 0
 },
 {
  "start": 871.6,
  "end": 872.1,
  "who": 2
 },
 {
  "start": 872.1,
  "end": 872.6,
  "who": 1
 },
 {
  "start": 872.6,
  "end": 873.03,
  "who": 4
 },
 {
  "start": 873.86,
  "end": 874.36,
  "who": 0
 },
 {
  "start": 874.36,
  "end": 875.86,
  "who": 3
 },
 {
  "start": 875.86,
  "end": 876.86,
  "who": 1
 },
 {
  "start": 877.36,
  "end": 877.86,
  "who": 2
 },
 {
  "start": 877.86,
  "end": 879.36,
  "who": 3
 },
 {
  "start": 879.36,
  "end": 879.86,
  "who": 4
 },
 {
  "start": 880.36,
  "end": 880.86,
  "who": 1
 },
 {
  "start": 880.86,
  "end": 881.36,
  "who": 3
 },
 {
  "start": 881.46,
  "end": 881.96,
  "who": 2
 },
 {
  "start": 881.96,
  "end": 882.46,
  "who": 1
 },
 {
  "start": 882.46,
  "end": 882.96,
  "who": 3
 },
 {
  "start": 883.46,
  "end": 883.96,
  "who": 1
 },
 {
  "start": 883.96,
  "end": 886.96,
  "who": 2
 },
 {
  "start": 887.46,
  "end": 889.46,
  "who": 2
 },
 {
  "start": 889.59,
  "end": 893.59,
  "who": 2
 },
 {
  "start": 893.59,
  "end": 894.09,
  "who": 4
 },
 {
  "start": 894.09,
  "end": 894.59,
  "who": 2
 },
 {
  "start": 894.59,
  "end": 895.09,
  "who": 0
 },
 {
  "start": 895.09,
  "end": 895.86,
  "who": 2
 },
 {
  "start": 895.98,
  "end": 896.48,
  "who": 2
 },
 {
  "start": 896.48,
  "end": 896.98,
  "who": 0
 },
 {
  "start": 896.98,
  "end": 899.98,
  "who": 2
 },
 {
  "start": 899.98,
  "end": 900.48,
  "who": 3
 },
 {
  "start": 900.48,
  "end": 902.98,
  "who": 2
 },
 {
  "start": 902.98,
  "end": 903.24,
  "who": 4
 }
]