[
 {
  "start": 1.74,
  "end": 2.74,
  "who": 0
 },
 {
  "start": 4.24,
  "end": 4.74,
  "who": 0
 },
 {
  "start": 7.17,
  "end": 9.67,
  "who": 0
 },
 {
  "start": 10.17,
  "end": 11.17,
  "who": 0
 },
 {
  "start": 13.17,
  "end": 14.67,
  "who": 0
 },
 {
  "start": 18.3,
  "end": 18.8,
  "who": 0
 },
 {
  "start": 19.3,
  "end": 19.8,
  "who": 0
 },
 {
  "start": 21.3,
  "end": 21.8,
  "who": 0
 },
 {
  "start": 28.93,
  "end": 30.43,
  "who": 0
 },
 {
  "start": 32.0,
  "end": 32.5,
  "who": 0
 },
 {
  "start": 33.5,
  "end": 34.0,
  "who": 0
 },
 {
  "start": 34.5,
  "end": 35.0,
  "who": 0
 },
 {
  "start": 36.08,
  "end": 37.08,
  "who": 0
 },
 {
  "start": 37.58,
  "end": 38.08,
  "who": 0
 },
 {
  "start": 42.72,
  "end": 43.22,
  "who": 0
 },
 {
  "start": 44.22,
  "end": 44.72,
  "who": 0
 },
 {
  "start": 45.22,
  "end": 46.72,
  "who": 0
 },
 {
  "start": 53.19,
  "end": 53.69,
  "who": 0
 },
 {
  "start": 55.19,
  "end": 56.19,
  "who": 0
 },
 {
  "start": 56.82,
  "end": 57.82,
  "who": 0
 },
 {
  "start": 60.58,
  "end": 60.96,
  "who": 0
 },
 {
  "start": 62.66,
  "end": 63.16,
  "who": 0
 },
 {
  "start": 64.66,
  "end": 68.16,
  "who": 0
 },
 {
  "start": 70.79,
  "end": 77.97,
  "who": 0
 },
 {
  "start": 78.3,
  "end": 79.74,
  "who": 0
 },
 {
  "start": 82.98,
  "end": 85.48,
  "who": 0
 },
 {
  "start": 85.98,
  "end": 87.48,
  "who": 0
 },
 {
  "start": 89.61,
  "end": 90.61,
  "who": 0
 },
 {
  "start": 91.61,
  "end": 96.11,
  "who": 0
 },
 {
  "start": 96.24,
  "end": 97.41,
  "who": 0
 },
 {
  "start": 100.62,
  "end": 101.62,
  "who": 0
 },
 {
  "start": 102.83,
  "end": 104.33,
  "who": 0
 },
 {
  "start": 104.85,
  "end": 105.35,
  "who": 0
 },
 {
  "start": 106.85,
  "end": 107.35,
  "who": 0
 },
 {
  "start": 107.85,
  "end": 108.35,
  "who": 0
 },
 {
  "start": 115.86,
  "end": 116.36,
  "who": 0
 },
 {
  "start": 117.36,
  "end": 117.86,
  "who": 0
 },
 {
  "start": 120.86,
  "end": 121.36,
  "who": 0
 },
 {
  "start": 123.36,
  "end": 123.86,
  "who": 0
 },
 {
  "start": 130.71,
  "end": 131.21,
  "who": 0
 },
 {
  "start": 137.6,
  "end": 138.1,
  "who": 0
 },
 {
  "start": 141.02,
  "end": 143.02,
  "who": 0
 },
 {
  "start": 145.29,
  "end": 146.79,
  "who": 0
 }
]