[
 {
  "start": 1.6400000000000001,
  "end": 4.28,
  "text": "Join the big Troms\u00f8 Cup!",
  "who": 3
 },
 {
  "start": 4.28,
  "end": 11.439999999999998,
  "text": "At Rema 1000 stores in Troms\u00f8 city, you get 40% of selected 1 liter milk and all of fresh bread with E.",
  "who": 3
 },
 {
  "start": 11.44,
  "end": 14.0,
  "text": "40% every Monday.",
  "who": 3
 },
 {
  "start": 14.0,
  "end": 16.2,
  "text": "You get the prize right in the cash register.",
  "who": 3
 },
 {
  "start": 16.2,
  "end": 19.56,
  "text": "Welcome to a nice and reasonable trade.",
  "who": 3
 },
 {
  "start": 19.56,
  "end": 30.16,
  "text": "Rema 1000, always at a low price.",
  "who": 0
 },
 {
  "start": 30.16,
  "end": 32.626666666666665,
  "text": "Welcome to the History Extra podcast.",
  "who": 0,
  "matched": true
 },
 {
  "start": 33.12,
  "end": 48.56,
  "text": "Fascinating historical conversations from BBC History Magazine and BBC History Review.",
  "who": 0
 },
 {
  "start": 48.56,
  "end": 53.2,
  "text": "This is the pioneering work of authors like Mary Shelley and H.G. Wells.",
  "who": 0
 },
 {
  "start": 53.2,
  "end": 58.08,
  "text": "The science fiction genre has attempted to divine the future and it's also reflected",
  "who": 0
 },
 {
  "start": 58.08,
  "end": 61.959999999999994,
  "text": "the hopes and fears of changing eras.",
  "who": 0
 },
 {
  "start": 61.96,
  "end": 67.64,
  "text": "In today's Everything You Want to Know episode, Professor Roger Luckhurst from Birkbeck University",
  "who": 0
 },
 {
  "start": 67.64,
  "end": 73.04,
  "text": "of London tackles listener questions and popular internet search queries about the history",
  "who": 0
 },
 {
  "start": 73.04,
  "end": 75.52,
  "text": "of all things sci fi.",
  "who": 0
 },
 {
  "start": 75.52,
  "end": 78.60000000000001,
  "text": "Supporting the questions to Roger was Matt Elton.",
  "who": 0
 },
 {
  "start": 78.42,
  "end": 80.70000000000002,
  "text": "So Roger, thank you so much for being with us today.",
  "who": 1,
  "matched": true
 },
 {
  "start": 80.88,
  "end": 84.7,
  "text": "We are going to run through in quite a short amount of time a quite a big subject which",
  "who": 1
 },
 {
  "start": 84.7,
  "end": 90.87999999999998,
  "text": "is the history of science fiction and what it tells us I suppose about history more generally.",
  "who": 1
 },
 {
  "start": 90.88,
  "end": 94.52,
  "text": "As always on these podcasts we've got some questions from people on social media, some",
  "who": 1
 },
 {
  "start": 94.52,
  "end": 99.28000000000002,
  "text": "questions from Google searches, some questions of my own to help tie things together.",
  "who": 1
 },
 {
  "start": 99.28000000000002,
  "end": 102.96000000000001,
  "text": "So we're going to get into some really exciting stuff later on but we need to start with some",
  "who": 1
 },
 {
  "start": 102.96000000000001,
  "end": 110.36,
  "text": "fairly dry unfortunately, although I don't know, they do tell us things about terminology.",
  "who": 1
 },
 {
  "start": 110.36,
  "end": 115.52,
  "text": "We've had a lot of questions in about what is science fiction, what is hard science fiction.",
  "who": 1
 },
 {
  "start": 115.52,
  "end": 119.16000000000001,
  "text": "There's a meme going around Twitter at the moment about the difference between fantasy",
  "who": 1
 },
 {
  "start": 119.16000000000001,
  "end": 120.68000000000004,
  "text": "and science fiction.",
  "who": 1
 },
 {
  "start": 120.68000000000004,
  "end": 123.68000000000004,
  "text": "I wondered if you could just set up some of those ideas for us.",
  "who": 1
 },
 {
  "start": 123.69,
  "end": 126.28999999999999,
  "text": "Oh let's start with the small thing first then.",
  "who": 2,
  "matched": true
 },
 {
  "start": 126.28999999999999,
  "end": 131.29,
  "text": "This is entirely uncontroversial and there'll be no complaints about this.",
  "who": 2
 },
 {
  "start": 131.29,
  "end": 135.92999999999998,
  "text": "Yeah so there is always what I call border policing.",
  "who": 2
 },
 {
  "start": 135.92999999999998,
  "end": 140.85,
  "text": "This is that kind of sense of people wanting to put really tight borders around.",
  "who": 2
 },
 {
  "start": 140.85,
  "end": 146.91666666666663,
  "text": "So the big opposition might be science fiction which is all about science and extrapolation",
  "who": 2,
  "matched": true
 },
 {
  "start": 147.08,
  "end": 155.6,
  "text": "and cognitive developments and technology versus either the gothic which is irrational,",
  "who": 2
 },
 {
  "start": 155.6,
  "end": 161.67999999999998,
  "text": "dreamlike, all about the unconscious, about our repressed anxieties.",
  "who": 2
 },
 {
  "start": 161.68,
  "end": 166.68,
  "text": "And depending on your view science fiction is fantastic and rational and the gothic is",
  "who": 2
 },
 {
  "start": 166.68,
  "end": 171.56,
  "text": "awful and dreary and you shouldn't go near it and it's the same with fantasy.",
  "who": 2
 },
 {
  "start": 171.56,
  "end": 174.88,
  "text": "This is what's happening at the moment is on the one hand you have science fiction,",
  "who": 2
 },
 {
  "start": 174.88,
  "end": 182.2,
  "text": "on the other hand you have hobbits and elves and people develop either a passion for elves",
  "who": 2
 },
 {
  "start": 182.2,
  "end": 184.95999999999998,
  "text": "or find them toxic in various ways.",
  "who": 2
 },
 {
  "start": 184.96,
  "end": 188.48,
  "text": "And they try and police the borders between these things.",
  "who": 2
 },
 {
  "start": 188.48,
  "end": 195.29999999999998,
  "text": "So science fiction emerged in the 1920s and initially in America it was seen as a kind",
  "who": 2
 },
 {
  "start": 195.3,
  "end": 198.52,
  "text": "of science literature of engineers.",
  "who": 2
 },
 {
  "start": 198.52,
  "end": 205.28,
  "text": "So there was a lot of policing of this must be extrapolation from science, you can't have",
  "who": 2
 },
 {
  "start": 205.28,
  "end": 207.6,
  "text": "this, you can't have that.",
  "who": 2
 },
 {
  "start": 207.6,
  "end": 211.8,
  "text": "You can have telepathy though weirdly because that's science somehow.",
  "who": 2,
  "matched": true
 },
 {
  "start": 211.8,
  "end": 216.40000000000003,
  "text": "Those sorts of issues and then they began to kind of define themselves as a serious",
  "who": 2
 },
 {
  "start": 216.40000000000003,
  "end": 222.48,
  "text": "literature against fantasy which is myth and dream and all that sort of stuff.",
  "who": 2
 },
 {
  "start": 222.48,
  "end": 228.55999999999997,
  "text": "So you get a lot of policing and a lot of angry Twitter storms about this.",
  "who": 2
 },
 {
  "start": 228.56,
  "end": 235.48,
  "text": "So we've had one recently about Tolkien because of the adaptation Rings of Power.",
  "who": 2
 },
 {
  "start": 235.48,
  "end": 239.96,
  "text": "And you also have arguments around Margaret Atwood saying that she doesn't write science",
  "who": 2
 },
 {
  "start": 239.96,
  "end": 245.31999999999996,
  "text": "fiction, she only writes speculative fiction and I think it's designed to kind of generate",
  "who": 2
 },
 {
  "start": 245.32,
  "end": 253.12,
  "text": "debate and it's fine if it forces you to think through what it is that a genre is.",
  "who": 2
 },
 {
  "start": 253.12,
  "end": 258.68,
  "text": "But I think the best position to have, maybe I'm just old, is to relax about those things",
  "who": 2
 },
 {
  "start": 258.68,
  "end": 262.96,
  "text": "because I think most fans don't police the border in that kind of way.",
  "who": 2
 },
 {
  "start": 262.96,
  "end": 266.87999999999994,
  "text": "They just, you know, they watch a horror film then they go and read Isaac Asimov, they don't",
  "who": 2
 },
 {
  "start": 266.87999999999994,
  "end": 270.2799999999999,
  "text": "really see any kind of boundaries between these different things.",
  "who": 2,
  "matched": true
 },
 {
  "start": 270.28,
  "end": 275.84,
  "text": "So I think I tend towards a much more relaxed attitude to this, partly because the history",
  "who": 2
 },
 {
  "start": 275.84,
  "end": 279.71999999999997,
  "text": "of science fiction criticism is all about shouting at what things aren't.",
  "who": 2
 },
 {
  "start": 279.72,
  "end": 285.4,
  "text": "You know, you cannot be let in or we do not want this stuff and nevertheless it's still",
  "who": 2
 },
 {
  "start": 285.4,
  "end": 287.12,
  "text": "there and people still read it.",
  "who": 2
 },
 {
  "start": 287.12,
  "end": 291.64,
  "text": "So why don't we obey what the readers do in fact?",
  "who": 2
 },
 {
  "start": 291.51,
  "end": 296.07000000000005,
  "text": "So some of it is about relaxing the policing of these boundaries so that more things are",
  "who": 1,
  "matched": true
 },
 {
  "start": 296.2,
  "end": 299.48,
  "text": "thought of or we don't need to think about those boundaries so much.",
  "who": 1
 },
 {
  "start": 299.48,
  "end": 305.0,
  "text": "I mean, it is something that seems to sort of animate people, not necessarily in a negative",
  "who": 1
 },
 {
  "start": 305.0,
  "end": 306.0,
  "text": "way.",
  "who": 1
 },
 {
  "start": 306.0,
  "end": 310.20000000000005,
  "text": "And another question, we've got a question from Liam Keogh here who says, what is considered",
  "who": 1
 },
 {
  "start": 310.20000000000005,
  "end": 313.52000000000004,
  "text": "the first science fiction literature and what themes did it cover?",
  "who": 1
 },
 {
  "start": 313.52000000000004,
  "end": 316.72,
  "text": "Now I know this taps into a whole other range of issues.",
  "who": 1
 },
 {
  "start": 316.72,
  "end": 320.12,
  "text": "I mean, his question is interesting though because what he's asking is what is generally",
  "who": 1
 },
 {
  "start": 320.12,
  "end": 323.48,
  "text": "considered to be, which I think is maybe a safer thing.",
  "who": 1
 },
 {
  "start": 323.48,
  "end": 328.56,
  "text": "Yeah, that is, that's right and I think the answer is that there are multiple answers",
  "who": 2
 },
 {
  "start": 328.56,
  "end": 331.08,
  "text": "so that I think we need to be aware of that.",
  "who": 2,
  "matched": true
 },
 {
  "start": 331.08,
  "end": 337.04,
  "text": "So many people say when HG Wells wrote The Time Machine and published it, it was called",
  "who": 2
 },
 {
  "start": 337.04,
  "end": 343.84,
  "text": "a scientific romance and then 30 years later in America, someone coined the really awkward",
  "who": 2
 },
 {
  "start": 343.84,
  "end": 350.12000000000006,
  "text": "phrase science fiction, which became science fiction in 1929, so there you go, quite straightforward",
  "who": 2
 },
 {
  "start": 350.12000000000006,
  "end": 351.12,
  "text": "naming.",
  "who": 2
 },
 {
  "start": 351.12,
  "end": 355.84000000000003,
  "text": "Actually, of course, there's a really long prehistory here and other people go for Mary",
  "who": 2
 },
 {
  "start": 355.84000000000003,
  "end": 362.12000000000006,
  "text": "Shelley's Frankenstein, which is 1818 and that certainly is a new kind of gothic, which",
  "who": 2
 },
 {
  "start": 362.12000000000006,
  "end": 367.5000000000001,
  "text": "is using science and materialism as the kind of basis for its horror, so generating the",
  "who": 2
 },
 {
  "start": 367.5000000000001,
  "end": 374.84000000000015,
  "text": "spark of life with electricity rather than any supernatural means, those sorts of debates",
  "who": 2
 },
 {
  "start": 374.84000000000015,
  "end": 375.88000000000017,
  "text": "around her.",
  "who": 2
 },
 {
  "start": 375.88000000000017,
  "end": 380.0000000000001,
  "text": "So you have a father of science fiction and a mother of science fiction, but then if you",
  "who": 2
 },
 {
  "start": 380.0000000000001,
  "end": 387.44000000000005,
  "text": "include utopian literature in this, of course, Moore's Utopia was written in 1516 and there",
  "who": 2
 },
 {
  "start": 387.44000000000005,
  "end": 392.9600000000001,
  "text": "are centuries of people who write and imagine utopias which might be in different spaces",
  "who": 2
 },
 {
  "start": 392.9600000000001,
  "end": 398.1200000000002,
  "text": "so they might be set somewhere else, but they're also often set in a different time so they",
  "who": 2
 },
 {
  "start": 398.1200000000002,
  "end": 402.44000000000017,
  "text": "might be in the future or they might be in the golden age of the past and all the way",
  "who": 2
 },
 {
  "start": 402.44000000000017,
  "end": 407.06000000000023,
  "text": "through particularly the 18th century, you have lots of people writing hundreds and hundreds",
  "who": 2
 },
 {
  "start": 407.06000000000023,
  "end": 413.80000000000024,
  "text": "and hundreds of utopias, women only ones, men only ones, you know, the end of all alienation,",
  "who": 2
 },
 {
  "start": 413.80000000000024,
  "end": 416.2000000000002,
  "text": "delight and so on.",
  "who": 2
 },
 {
  "start": 416.2000000000002,
  "end": 420.4800000000003,
  "text": "So there are lots of multiple kind of origins and I think that's the best way of thinking",
  "who": 2
 },
 {
  "start": 420.4800000000003,
  "end": 428.36000000000035,
  "text": "about it is that there are many answers to this question and that's also fine.",
  "who": 2
 },
 {
  "start": 428.24,
  "end": 432.67999999999995,
  "text": "And I think we'll get into Shelley and HG Wells, who you mentioned there, who were two",
  "who": 1,
  "matched": true
 },
 {
  "start": 432.87,
  "end": 437.15000000000003,
  "text": "really powerful and influential figures. I wanted to go back briefly to talk about utopias",
  "who": 1,
  "matched": true
 },
 {
  "start": 437.15000000000003,
  "end": 440.63000000000005,
  "text": "and this is an idea that I think we'll come back to a couple of times. What does it tell",
  "who": 1
 },
 {
  "start": 440.63000000000005,
  "end": 448.43,
  "text": "us that the idea of a utopia or various utopias was so compelling for people in the 18th century?",
  "who": 1
 },
 {
  "start": 447.84,
  "end": 452.15999999999997,
  "text": "Well I think it's a kind of an impulse that stays broadly the same all the way through",
  "who": 2,
  "matched": true
 },
 {
  "start": 452.68,
  "end": 459.8,
  "text": "from the beginning. So someone like Thomas Moore, he sets up a utopia on an island, utopos,",
  "who": 2
 },
 {
  "start": 459.8,
  "end": 466.16,
  "text": "which means no place, but also the good place, so it's like a pun. And it's quite clearly",
  "who": 2
 },
 {
  "start": 466.16,
  "end": 472.63999999999993,
  "text": "a sort of political statement about what the hell's wrong with England and what you could",
  "who": 2
 },
 {
  "start": 472.64,
  "end": 477.94,
  "text": "do to put it right in your imagined kind of space. And actually Plato's Republic might",
  "who": 2
 },
 {
  "start": 477.94,
  "end": 485.16,
  "text": "be regarded as one of those, except that he banishes all poets and artists, so a bit tricky.",
  "who": 2
 },
 {
  "start": 485.16,
  "end": 492.76000000000005,
  "text": "In the 18th century you have a huge eruption of those utopias because I guess we're at",
  "who": 2
 },
 {
  "start": 492.76000000000005,
  "end": 502.4000000000001,
  "text": "the beginnings of a new economic form, capitalism, and that causes some people to kind of rush",
  "who": 2
 },
 {
  "start": 502.4000000000001,
  "end": 507.3600000000001,
  "text": "ahead in their mercantile adventures, but clearly there is also a cost to that, there's",
  "who": 2
 },
 {
  "start": 507.3600000000001,
  "end": 512.3000000000001,
  "text": "a change, it's a shift that people find very traumatic. And so they're trying to imagine",
  "who": 2
 },
 {
  "start": 512.3000000000001,
  "end": 518.0000000000002,
  "text": "alternatives, other kind of ways of doing things. One of my favourite utopianists is",
  "who": 2
 },
 {
  "start": 518.0000000000002,
  "end": 526.7200000000003,
  "text": "Charles Fourier, and he formed a whole movement of Fourierism, and he went through the French",
  "who": 2
 },
 {
  "start": 526.7200000000003,
  "end": 534.7600000000002,
  "text": "Revolution in 1789, his family lost all of its money, he had a miserable time as someone",
  "who": 2
 },
 {
  "start": 534.7600000000002,
  "end": 539.6400000000001,
  "text": "who was a merchant and then lost his living basically, and he retreated and wrote this",
  "who": 2
 },
 {
  "start": 539.6400000000001,
  "end": 545.1200000000002,
  "text": "whole sequence of very extraordinary books, which was his imagined perfect utopia which",
  "who": 2
 },
 {
  "start": 545.1200000000002,
  "end": 553.4800000000004,
  "text": "only had 1620 people in it, and lived in this collective house, and everyone could combine",
  "who": 2
 },
 {
  "start": 553.4800000000004,
  "end": 557.9200000000003,
  "text": "with everyone else, there was no alienated labour, everyone could have sex with everybody",
  "who": 2
 },
 {
  "start": 557.9200000000003,
  "end": 563.2000000000004,
  "text": "else, it was all lovely. In fact it was so lovely that this would produce a wholesale",
  "who": 2
 },
 {
  "start": 563.2000000000004,
  "end": 570.8800000000003,
  "text": "change in the earth itself, so that the sea would turn into lemonade that would be drinkable.",
  "who": 2
 },
 {
  "start": 570.8800000000003,
  "end": 577.2800000000003,
  "text": "Of course, and this sort of wonderful utopian kind of imagining, and even if it's slightly",
  "who": 2
 },
 {
  "start": 577.2800000000003,
  "end": 583.4000000000003,
  "text": "mad, it had a really big influence on things like Marxism and utopian communities in America",
  "who": 2
 },
 {
  "start": 583.4000000000003,
  "end": 587.7600000000003,
  "text": "all the way through the 19th century, so you know you have these mad dreams that nevertheless",
  "who": 2
 },
 {
  "start": 587.7600000000003,
  "end": 592.8800000000003,
  "text": "people pick up and run with and try and explore in various kinds of ways. And that's what",
  "who": 2
 },
 {
  "start": 592.8800000000003,
  "end": 597.7200000000004,
  "text": "science fiction does too, you know, it takes our present and sort of nudges some things",
  "who": 2
 },
 {
  "start": 597.7200000000004,
  "end": 599.3600000000004,
  "text": "slightly into the future.",
  "who": 2
 },
 {
  "start": 598.94,
  "end": 604.94,
  "text": "So it's both informed by and informs historical kind of reality of the past, if that makes",
  "who": 1,
  "matched": true
 },
 {
  "start": 605.56,
  "end": 606.56,
  "text": "sense?",
  "who": 1
 },
 {
  "start": 606.56,
  "end": 610.28,
  "text": "Yeah, it does make sense because what you, I think you say, so none of us know what the",
  "who": 2
 },
 {
  "start": 610.28,
  "end": 616.6000000000001,
  "text": "future is, right, and we don't know from minute to minute, but you extrapolate certain things.",
  "who": 2
 },
 {
  "start": 616.6000000000001,
  "end": 621.6000000000003,
  "text": "So some people say that science fiction is a literature of extrapolation, so you take",
  "who": 2
 },
 {
  "start": 621.6000000000003,
  "end": 626.5200000000003,
  "text": "a device that's just emerged, something like a mobile phone, and you just nudge it. What's",
  "who": 2
 },
 {
  "start": 626.5200000000003,
  "end": 631.0400000000004,
  "text": "it going to be like? What's it going to do to us in 50 years time? Because it does change",
  "who": 2
 },
 {
  "start": 631.0400000000004,
  "end": 636.8800000000006,
  "text": "our brains, in fact, you know, it changes our attention span, it changes how we communicate",
  "who": 2
 },
 {
  "start": 636.8800000000006,
  "end": 640.8000000000005,
  "text": "with each other. What's going to happen in 50 years time if you just extrapolate from",
  "who": 2
 },
 {
  "start": 640.8000000000005,
  "end": 647.3400000000006,
  "text": "that one device forward? So that's quite often a common way of thinking about science fiction.",
  "who": 2
 },
 {
  "start": 647.3400000000006,
  "end": 653.2800000000005,
  "text": "In other words, it's as much about the present and how we're imagining future than it is",
  "who": 2
 },
 {
  "start": 653.2800000000005,
  "end": 657.0000000000007,
  "text": "about the future, because of course, many of them are wrong. Some of them are sometimes",
  "who": 2
 },
 {
  "start": 657.0000000000007,
  "end": 662.0800000000008,
  "text": "weirdly right, but actually, most of the time it's wrong, but that doesn't matter. It's",
  "who": 2
 },
 {
  "start": 662.0800000000008,
  "end": 667.2000000000008,
  "text": "not about that. It's about how we right now imagine our future or can't imagine a future,",
  "who": 2
 },
 {
  "start": 667.2000000000008,
  "end": 672.3400000000008,
  "text": "you know, so we're full of apocalyptic, doom laden dystopias at the moment because of climate",
  "who": 2
 },
 {
  "start": 672.3400000000008,
  "end": 678.5600000000007,
  "text": "change and other issues. Can we imagine a future? It's really difficult in this scenario",
  "who": 2
 },
 {
  "start": 678.5600000000007,
  "end": 683.7600000000007,
  "text": "to imagine a future, but some people nevertheless use science fiction to try. Someone like Kim",
  "who": 2
 },
 {
  "start": 683.7600000000007,
  "end": 689.8400000000008,
  "text": "Stanley Robinson says he has a commitment to write utopias because you need to offer",
  "who": 2
 },
 {
  "start": 689.8400000000008,
  "end": 693.9200000000006,
  "text": "solutions to what seem like utterly intractable problems.",
  "who": 2
 },
 {
  "start": 693.6,
  "end": 697.62,
  "text": "Something that I think is really interesting is that some of these ideas have proven so",
  "who": 1,
  "matched": true
 },
 {
  "start": 697.94,
  "end": 703.4,
  "text": "powerful and so long lasting, it can be hard to keep in mind just how long ago they were",
  "who": 1
 },
 {
  "start": 703.4,
  "end": 708.2799999999999,
  "text": "written. So Sweden Hungry on Twitter was among the many people to ask about Frankenstein,",
  "who": 1
 },
 {
  "start": 708.28,
  "end": 713.88,
  "text": "which you've talked about previously. Is it right to see Gothic literature, which I suppose",
  "who": 1
 },
 {
  "start": 713.88,
  "end": 720.4800000000001,
  "text": "Frankenstein partly fits, as being the genre from which science fiction emerged?",
  "who": 1
 },
 {
  "start": 720.48,
  "end": 727.92,
  "text": "In some respects, yes. So the Gothic, which people tend to say is emerging in the 1760s,",
  "who": 2
 },
 {
  "start": 727.92,
  "end": 735.4800000000001,
  "text": "so some people say that the first Gothic romance is Horace Walpole's The Castle of Otranto,",
  "who": 2
 },
 {
  "start": 735.4800000000001,
  "end": 742.2400000000002,
  "text": "which came out in 1764. By the time you get to the end of that really major wave, so Mary",
  "who": 2
 },
 {
  "start": 742.2400000000002,
  "end": 750.1600000000001,
  "text": "Shelley's Frankenstein is 1818, there is definitely a shift, which I always say is",
  "who": 2
 },
 {
  "start": 750.1600000000001,
  "end": 755.9600000000002,
  "text": "about a move from the authority of religion. So there's a kind of terror in the early",
  "who": 2
 },
 {
  "start": 755.9600000000002,
  "end": 764.1600000000001,
  "text": "Gothic, particularly of Catholicism and of priestcraft and tyranny and superstition,",
  "who": 2
 },
 {
  "start": 764.1600000000001,
  "end": 770.4600000000002,
  "text": "but nevertheless a dreaded fear of what's going to happen to the soul. And in Frankenstein,",
  "who": 2
 },
 {
  "start": 770.4600000000002,
  "end": 776.52,
  "text": "it's all about the kind of religious framing of that, very scandalously, because Mary and",
  "who": 2
 },
 {
  "start": 776.52,
  "end": 784.0,
  "text": "Percy Shelley were publicly atheists, which was a very daring and dramatic position to",
  "who": 2
 },
 {
  "start": 784.0,
  "end": 789.48,
  "text": "have and actually, you know, it was illegal to publish things on those kinds of topics",
  "who": 2
 },
 {
  "start": 789.48,
  "end": 796.06,
  "text": "quite often. But it's an entirely scientific frame for Frankenstein. So this is getting",
  "who": 2
 },
 {
  "start": 796.06,
  "end": 803.5999999999999,
  "text": "together really gruesomely body parts, arguing that the spark of life, the vitalist spark",
  "who": 2
 },
 {
  "start": 803.6,
  "end": 812.08,
  "text": "is electricity. Mary Shelley went to see exhibitions of frogs legs famously being sparked after",
  "who": 2
 },
 {
  "start": 812.08,
  "end": 816.4799999999999,
  "text": "apparent death. They seem to be alive. And they did lots of gruesome experiments on recently",
  "who": 2
 },
 {
  "start": 816.48,
  "end": 820.04,
  "text": "executed prisoners where they were trying to spark them to life just after they'd been",
  "who": 2
 },
 {
  "start": 820.04,
  "end": 827.2,
  "text": "executed, hanged. And so that's a scientific frame. The horrors now are the things that",
  "who": 2
 },
 {
  "start": 827.2,
  "end": 833.24,
  "text": "man can do. So the kind of subtitle of Frankenstein is a modern Prometheus because Prometheus",
  "who": 2
 },
 {
  "start": 833.24,
  "end": 838.2,
  "text": "stole the fire from the gods. And here we've got a story, the classic story, the Frankenstein",
  "who": 2
 },
 {
  "start": 838.2,
  "end": 844.6400000000001,
  "text": "science story of a scientist who steals the kind of godly power to create life. So it's",
  "who": 2
 },
 {
  "start": 844.6400000000001,
  "end": 850.0800000000003,
  "text": "a totally different paradigm by that point. And that's what begins to, I think, there's",
  "who": 2
 },
 {
  "start": 850.0800000000003,
  "end": 855.8800000000002,
  "text": "a good argument for arguing that the authority of science grows and grows and grows in the",
  "who": 2
 },
 {
  "start": 855.8800000000002,
  "end": 861.0800000000003,
  "text": "19th century. So that by the time you get to HG Wells, he is one of the first people",
  "who": 2
 },
 {
  "start": 861.0800000000003,
  "end": 868.0800000000003,
  "text": "to be trained to teach science in schools and universities. This hadn't happened before.",
  "who": 2
 },
 {
  "start": 868.0800000000003,
  "end": 873.1200000000002,
  "text": "It's all the authority of the classics and of theology that is being displaced and Wells",
  "who": 2
 },
 {
  "start": 873.1200000000002,
  "end": 878.3600000000002,
  "text": "is the kind of product of that. But Mary Shelley is the first kind of early flag wave.",
  "who": 2,
  "matched": true
 },
 {
  "start": 878.36,
  "end": 883.76,
  "text": "And Shelley and her work really encapsulate, is it fair to say, a moment of shifting in",
  "who": 1
 },
 {
  "start": 883.76,
  "end": 888.1200000000001,
  "text": "society between the importance of religion and the importance of science. Does it tell",
  "who": 1
 },
 {
  "start": 888.1200000000001,
  "end": 891.5600000000001,
  "text": "us anything else about that particular moment in time?",
  "who": 1
 },
 {
  "start": 891.15,
  "end": 896.3499999999999,
  "text": "It tells us an awful lot, actually. And this is the case of, I think, any book that you",
  "who": 2,
  "matched": true
 },
 {
  "start": 896.76,
  "end": 903.6,
  "text": "put in historical context, but particularly Mary and Percy Shelley, who were these radicals",
  "who": 2
 },
 {
  "start": 903.6,
  "end": 913.2000000000002,
  "text": "and dissidents, scandalous figures who were interested in science and medicine and explored",
  "who": 2
 },
 {
  "start": 913.2000000000002,
  "end": 917.6400000000001,
  "text": "different kinds of ways of living. So they went into exile because they were so kind",
  "who": 2
 },
 {
  "start": 917.6400000000001,
  "end": 921.84,
  "text": "of scandalous. And it's not just Frankenstein because Mary Shelley went on to write The",
  "who": 2
 },
 {
  "start": 921.84,
  "end": 927.6,
  "text": "Last Man in 1826, which people have been reading very closely in the last two years because",
  "who": 2
 },
 {
  "start": 927.6,
  "end": 932.2400000000001,
  "text": "it's about a pandemic. And it's one of the first Last Man books. In other words, everyone",
  "who": 2
 },
 {
  "start": 932.2400000000001,
  "end": 938.1600000000001,
  "text": "kind of dies off and you have one figure. And that's an amazing description of the slow",
  "who": 2
 },
 {
  "start": 938.1600000000001,
  "end": 944.8000000000001,
  "text": "spread of a fatal disease from the East and the sort of panic that happens and the emptying",
  "who": 2
 },
 {
  "start": 944.8000000000001,
  "end": 951.76,
  "text": "out of London. It's very spooky to read. It even has a politician, he's a prime minister,",
  "who": 2
 },
 {
  "start": 951.76,
  "end": 958.52,
  "text": "he is relentlessly optimistic and says, fine, it's fine, it won't touch us at all. So reading",
  "who": 2
 },
 {
  "start": 958.52,
  "end": 963.2,
  "text": "that, you just think this is truly extraordinary, actually, that one of those origins there",
  "who": 2
 },
 {
  "start": 963.2,
  "end": 969.6800000000001,
  "text": "is. And it's all scientific, right? It's all about viruses and medicine and pandemic. It's",
  "who": 2
 },
 {
  "start": 969.6800000000001,
  "end": 974.7200000000001,
  "text": "not a kind of religious basis for that vision.",
  "who": 2
 },
 {
  "start": 974.72,
  "end": 981.0,
  "text": "So moving on to HG Wells, Gavin Griffiths on Twitter asks, was HG Wells the first writer",
  "who": 1
 },
 {
  "start": 981.0,
  "end": 984.6399999999999,
  "text": "to think of time travel or a time machine?",
  "who": 1
 },
 {
  "start": 984.64,
  "end": 992.72,
  "text": "That's also a cause for debate because there is a Spanish book that's been recently translated,",
  "who": 2
 },
 {
  "start": 992.72,
  "end": 998.96,
  "text": "which is just a little bit before, which some people argue has a time machine in it. But",
  "who": 2
 },
 {
  "start": 998.96,
  "end": 1006.72,
  "text": "the idea of displacement in time is basically a narrative trick of quite a lot of fiction,",
  "who": 2
 },
 {
  "start": 1006.95,
  "end": 1012.23,
  "text": "isn't it? So we have flashbacks or we have flash forwards. The good stories don't often",
  "who": 2,
  "matched": true
 },
 {
  "start": 1012.23,
  "end": 1018.27,
  "text": "go in a linear way, but they kind of jump around in time, I think. One of the really",
  "who": 2
 },
 {
  "start": 1018.27,
  "end": 1024.31,
  "text": "interesting points of reference here, which people might be interested in reading is Charles",
  "who": 2
 },
 {
  "start": 1024.31,
  "end": 1029.5500000000002,
  "text": "Dickens's short story The Signalman, which is a ghost story. It's a Christmas ghost story.",
  "who": 2
 },
 {
  "start": 1029.5500000000002,
  "end": 1039.3100000000002,
  "text": "And it's about a signalman on a railway who keeps seeing a vision of a man flagging in",
  "who": 2
 },
 {
  "start": 1039.3100000000002,
  "end": 1044.83,
  "text": "absolute panic, you know, as if to kind of shut down what's happening and to kind of",
  "who": 2
 },
 {
  "start": 1044.83,
  "end": 1050.8700000000003,
  "text": "ruin the ending. He's actually seeing himself in the future. So it's like a time travel",
  "who": 2
 },
 {
  "start": 1050.8700000000003,
  "end": 1056.07,
  "text": "ghost story. So it's no longer a ghost of the past, which is what the Gothic's about,",
  "who": 2
 },
 {
  "start": 1056.07,
  "end": 1061.11,
  "text": "but it's a ghost from the future. It's yourself signalling to yourself. And that seems to",
  "who": 2
 },
 {
  "start": 1061.11,
  "end": 1066.5899999999997,
  "text": "me like a really critical moment in which people are imagining what effects do the future",
  "who": 2
 },
 {
  "start": 1066.5899999999997,
  "end": 1071.59,
  "text": "have on us, not just the past. So I think that's a good point of reference.",
  "who": 2
 },
 {
  "start": 1071.36,
  "end": 1074.6,
  "text": "We should talk a little bit about H.G. Wells in some depth because I think he's one of",
  "who": 1
 },
 {
  "start": 1074.6,
  "end": 1078.92,
  "text": "those figures who is really influential. And there's three books I want to talk about.",
  "who": 1
 },
 {
  "start": 1078.92,
  "end": 1084.6400000000003,
  "text": "One is The Time Machine. What does The Time Machine tell us about the Victorian era and",
  "who": 1,
  "matched": true
 },
 {
  "start": 1084.6400000000003,
  "end": 1086.6000000000001,
  "text": "I suppose its preoccupations?",
  "who": 1
 },
 {
  "start": 1086.6,
  "end": 1094.32,
  "text": "Yeah, The Time Machine by H.G. Wells is so important. So it came out in 1895 and was",
  "who": 2
 },
 {
  "start": 1094.32,
  "end": 1101.24,
  "text": "immediately kind of considered a work of genius. And he was on his way immediately writing",
  "who": 2
 },
 {
  "start": 1101.24,
  "end": 1106.9999999999998,
  "text": "an extraordinary sequence of books, which are very influential on science fiction after",
  "who": 2
 },
 {
  "start": 1107.0,
  "end": 1114.72,
  "text": "that. But it is very distinctly a portrait of London in the 1890s. So although he travels",
  "who": 2
 },
 {
  "start": 1114.72,
  "end": 1121.8,
  "text": "forward 800,000 years on his machine, what he's describing in that future society is",
  "who": 2
 },
 {
  "start": 1121.8,
  "end": 1127.84,
  "text": "a classical division between, you know, the capitalist workers who live underground to",
  "who": 2
 },
 {
  "start": 1127.84,
  "end": 1133.9600000000003,
  "text": "these feral kind of creatures who've devolved back into forms of repeatedly described as",
  "who": 2
 },
 {
  "start": 1133.9600000000003,
  "end": 1141.7600000000002,
  "text": "monkeys or as spiders who kind of live underground. And then this ethete decadent group of people",
  "who": 2
 },
 {
  "start": 1141.7600000000002,
  "end": 1148.7600000000004,
  "text": "who live on the surface, who seem very benign initially, but actually are slowly dying out",
  "who": 2
 },
 {
  "start": 1148.7600000000004,
  "end": 1154.9600000000003,
  "text": "and being literally fed on by the Morlocks. And H.G. Wells was from a lower middle class",
  "who": 2
 },
 {
  "start": 1154.9600000000003,
  "end": 1163.5200000000004,
  "text": "family. He was from trade. So he was not a person of the elite. The literary elite didn't",
  "who": 2
 },
 {
  "start": 1163.5200000000004,
  "end": 1169.4800000000005,
  "text": "like him at all. He didn't like them very much. And he was someone who was writing a",
  "who": 2
 },
 {
  "start": 1169.4800000000005,
  "end": 1174.1600000000003,
  "text": "kind of literature of the lower middle class as a science professional. He started out",
  "who": 2
 },
 {
  "start": 1174.1600000000003,
  "end": 1179.8800000000003,
  "text": "writing textbooks. So, you know, here's someone who is coming from a different locus of knowledge.",
  "who": 2
 },
 {
  "start": 1179.8800000000003,
  "end": 1183.88,
  "text": "But also he has a kind of socialist politics as well at this point and is sort of saying",
  "who": 2
 },
 {
  "start": 1183.88,
  "end": 1192.12,
  "text": "that the workers in a gruesome way will overthrow their oppressors. So he's very kind of bound",
  "who": 2
 },
 {
  "start": 1192.12,
  "end": 1198.1999999999998,
  "text": "up in that. And it's an amazing portrait, actually, of the decadence of the 1890s as",
  "who": 2
 },
 {
  "start": 1198.2,
  "end": 1204.96,
  "text": "well as this sense of the organisation of the working class, which was so feared at",
  "who": 2
 },
 {
  "start": 1204.96,
  "end": 1210.56,
  "text": "the end of the 19th century. Mob riots and, you know, stones being thrown for heaven's",
  "who": 2
 },
 {
  "start": 1210.56,
  "end": 1217.08,
  "text": "sake at gentlemen's clubs in Polnol. You know, all of that sort of anxiety about the",
  "who": 2
 },
 {
  "start": 1217.08,
  "end": 1224.3199999999997,
  "text": "upper T working classes. So it's incredibly bound up in the moment that he wrote. And",
  "who": 2
 },
 {
  "start": 1224.32,
  "end": 1229.44,
  "text": "that's what makes it interesting, I think. So less a sort of sense of, is this an effective",
  "who": 2
 },
 {
  "start": 1229.44,
  "end": 1234.9,
  "text": "vision of the future? Well, no, because its vision of the future is bound up with theories",
  "who": 2
 },
 {
  "start": 1234.9,
  "end": 1242.0,
  "text": "in the 1890s about decline and degeneration and entropy. It's fully a Victorian vision",
  "who": 2
 },
 {
  "start": 1242.0,
  "end": 1243.0,
  "text": "actually.",
  "who": 2
 },
 {
  "start": 1243.0,
  "end": 1248.08,
  "text": "Could you tell us something about the ways in which science fed into politics and political",
  "who": 1
 },
 {
  "start": 1248.08,
  "end": 1249.6,
  "text": "ideas in that period?",
  "who": 1
 },
 {
  "start": 1249.95,
  "end": 1255.55,
  "text": "Yes, it really does. So I think one of the switches that happens in the 19th century",
  "who": 2,
  "matched": true
 },
 {
  "start": 1256.44,
  "end": 1263.76,
  "text": "is the building basically of a scientific culture and a set of institutions. So it's",
  "who": 2
 },
 {
  "start": 1263.76,
  "end": 1269.5999999999997,
  "text": "only after the Education Act in 1870 that science begins to come into the school curriculum",
  "who": 2
 },
 {
  "start": 1269.6,
  "end": 1275.64,
  "text": "and into the university curriculum. The word scientist isn't used until the 20th century,",
  "who": 2
 },
 {
  "start": 1275.64,
  "end": 1279.0400000000002,
  "text": "although it had been coined in the 1830s, no one was really using it because it's not",
  "who": 2,
  "matched": true
 },
 {
  "start": 1279.0400000000002,
  "end": 1285.9200000000003,
  "text": "a profession. No one can do this. T.H. Huxley, one of the most famous scientists in the 19th",
  "who": 2
 },
 {
  "start": 1285.9200000000003,
  "end": 1291.8800000000006,
  "text": "century, basically had to have a subscription so that he could retire because he made no",
  "who": 2
 },
 {
  "start": 1291.8800000000006,
  "end": 1297.6000000000008,
  "text": "money from this. There was no kind of career. He didn't have a private stash of cash. So",
  "who": 2
 },
 {
  "start": 1297.6000000000008,
  "end": 1305.3200000000008,
  "text": "there is no career. But H.G. Wells is kind of an emblem of the emergence of funded science",
  "who": 2
 },
 {
  "start": 1305.3200000000008,
  "end": 1312.3200000000006,
  "text": "and of the authority of science and of the emergence. In the 1890s, you're getting huge",
  "who": 2
 },
 {
  "start": 1312.3200000000006,
  "end": 1322.6400000000003,
  "text": "strides in physics, in biology, discovery of bacteria and viruses and how they work,",
  "who": 2
 },
 {
  "start": 1322.6400000000003,
  "end": 1328.9200000000003,
  "text": "X rays, all kinds of new technological advances. And it really did feel like it was hurtling",
  "who": 2
 },
 {
  "start": 1328.9200000000003,
  "end": 1334.6000000000004,
  "text": "forward with science and technology. And it's Wells's training that gives him the ability",
  "who": 2
 },
 {
  "start": 1334.6000000000004,
  "end": 1342.4400000000003,
  "text": "to ride that storm and sort of filter it down into narratives that are really compelling.",
  "who": 2
 },
 {
  "start": 1342.4400000000003,
  "end": 1347.1600000000003,
  "text": "Whereas other people were really fearful of this. They would say, well, I can't cope with",
  "who": 2,
  "matched": true
 },
 {
  "start": 1347.1600000000003,
  "end": 1351.3200000000004,
  "text": "the speed of life. I mean, there are at least four evening newspapers and I get 10 telegrams",
  "who": 2
 },
 {
  "start": 1351.3200000000004,
  "end": 1356.5600000000004,
  "text": "a day. What on earth am I going to do with this? My brain is completely fried. I suffer",
  "who": 2
 },
 {
  "start": 1356.5600000000004,
  "end": 1363.1600000000005,
  "text": "from what they called Londonism, which was a kind of a disease of overstimulation, that",
  "who": 2
 },
 {
  "start": 1363.1600000000005,
  "end": 1369.6000000000006,
  "text": "you were going to decline and degenerate and unravel because of the speed of modernity.",
  "who": 2
 },
 {
  "start": 1369.6000000000006,
  "end": 1375.4000000000003,
  "text": "And I guess, you know, traffic did go faster in 1895 than it does now. So maybe they were",
  "who": 2
 },
 {
  "start": 1375.4000000000003,
  "end": 1377.7600000000002,
  "text": "suffering from speed.",
  "who": 2
 },
 {
  "start": 1377.09,
  "end": 1382.05,
  "text": "I mean, that's fascinating, particularly if we then think about 1896 is the island of",
  "who": 1,
  "matched": true
 },
 {
  "start": 1382.32,
  "end": 1388.0,
  "text": "Dr. Moreau. Is that also a book about fear of what might happen to society and about",
  "who": 1
 },
 {
  "start": 1388.0,
  "end": 1390.44,
  "text": "what society has already become as well?",
  "who": 1
 },
 {
  "start": 1390.44,
  "end": 1396.96,
  "text": "Yes. So the island of Dr. Moreau, which came out the year after the time machine is, you",
  "who": 2
 },
 {
  "start": 1396.96,
  "end": 1403.1599999999999,
  "text": "know, it gives you another branch of this crossover between Gothic and science fiction,",
  "who": 2
 },
 {
  "start": 1403.16,
  "end": 1408.24,
  "text": "I think, because it is truly gruesome. It's about a doctor who is in and on an isolated",
  "who": 2
 },
 {
  "start": 1408.24,
  "end": 1415.5200000000002,
  "text": "island is basically splicing up animals and producing new horrific creatures and then",
  "who": 2
 },
 {
  "start": 1415.5200000000002,
  "end": 1422.3200000000002,
  "text": "trying to educate them, give them language, turn them into human beings, give them this",
  "who": 2
 },
 {
  "start": 1422.3200000000002,
  "end": 1427.76,
  "text": "kind of sense of humanity. And of course, it all goes horrifically wrong and they degenerate",
  "who": 2
 },
 {
  "start": 1427.76,
  "end": 1433.8800000000003,
  "text": "back into their animalistic kind of forms. But there's a real kind of sense of glee here",
  "who": 2
 },
 {
  "start": 1433.8800000000003,
  "end": 1441.4000000000005,
  "text": "about the imagination that Darwin has given to the public, because suddenly millions of",
  "who": 2
 },
 {
  "start": 1441.4000000000005,
  "end": 1447.9600000000005,
  "text": "years in the past, what do we retain from all of that ancestry, this biological ancestry?",
  "who": 2
 },
 {
  "start": 1447.9600000000005,
  "end": 1452.9200000000005,
  "text": "But also what's going to happen in the future? You know, is this Darwin was quite comforting",
  "who": 2
 },
 {
  "start": 1452.9200000000005,
  "end": 1458.8000000000002,
  "text": "in some ways. He was very careful to say that, don't worry, the advance is upwards towards",
  "who": 2
 },
 {
  "start": 1458.8000000000002,
  "end": 1466.16,
  "text": "perfectibility. It was very kind of compatible, if you like, with a kind of benign, even religious",
  "who": 2
 },
 {
  "start": 1466.16,
  "end": 1471.24,
  "text": "sort of conception of we're heading towards perfection. But in the in the late 19th century,",
  "who": 2
 },
 {
  "start": 1471.24,
  "end": 1474.4800000000002,
  "text": "people were saying, hang on a minute, if you can go up the evolutionary chain, you can",
  "who": 2
 },
 {
  "start": 1474.4800000000002,
  "end": 1478.8800000000006,
  "text": "also slide back down it. And that's what happens, say, in Jekyll and Hyde. You know, Jekyll",
  "who": 2
 },
 {
  "start": 1478.8800000000006,
  "end": 1485.5600000000004,
  "text": "keeps taking his mysterious white powder and he degenerates back into this kind of animalistic",
  "who": 2
 },
 {
  "start": 1485.5600000000004,
  "end": 1494.1600000000003,
  "text": "form. And that was a that was a sheer terror of this theory of degeneration. So not advancing,",
  "who": 2
 },
 {
  "start": 1494.1600000000003,
  "end": 1500.8,
  "text": "but declining. And was that a portrait of what was going to happen to England? You know,",
  "who": 2
 },
 {
  "start": 1500.8,
  "end": 1504.32,
  "text": "you have a decline in full narrative. This is the height of the empire. But where else",
  "who": 2
 },
 {
  "start": 1504.32,
  "end": 1510.36,
  "text": "is there to go? Down. You know, so that's a sense of this is England at its imperial",
  "who": 2
 },
 {
  "start": 1510.36,
  "end": 1516.24,
  "text": "pomp. But it's full of this terrified imagination that actually we are going to decline and",
  "who": 2
 },
 {
  "start": 1516.24,
  "end": 1521.64,
  "text": "fall. And that sort of haunting is really important in Wells. It's why Wells is constantly",
  "who": 2
 },
 {
  "start": 1521.64,
  "end": 1527.8800000000003,
  "text": "arguing for different utopian kind of outcomes. If we stay on this course, he's suggesting",
  "who": 2
 },
 {
  "start": 1527.8800000000003,
  "end": 1532.7600000000002,
  "text": "then we will decline. So what we need is is a different organisation of society.",
  "who": 2
 },
 {
  "start": 1532.76,
  "end": 1538.28,
  "text": "And the idea of imperial decline and fall is, I think, also central to War of the Worlds,",
  "who": 1
 },
 {
  "start": 1538.28,
  "end": 1543.76,
  "text": "which I think is 1898. Does that tell us something about the Victorian Empire, the British Empire",
  "who": 1
 },
 {
  "start": 1543.76,
  "end": 1548.48,
  "text": "at this point in history? Yes, it does. I mean, the beginning of the",
  "who": 2
 },
 {
  "start": 1548.48,
  "end": 1554.96,
  "text": "War of the Worlds is this brilliant opening, you know, so people can find this on the net",
  "who": 2
 },
 {
  "start": 1554.96,
  "end": 1559.96,
  "text": "immediately. Just just read the opening kind of couple of pages because it's this brilliant",
  "who": 2
 },
 {
  "start": 1560.03,
  "end": 1566.2966666666666,
  "text": "trick of what science fiction can do. So it's kind of saying here we are, the English, British",
  "who": 2,
  "matched": true
 },
 {
  "start": 1566.48,
  "end": 1572.8,
  "text": "Empire is at its height. We are the most superior creatures on the planet. But what if there",
  "who": 2
 },
 {
  "start": 1572.8,
  "end": 1577.5599999999997,
  "text": "was an even greater kind of superior kind of power that was looking down at us? What",
  "who": 2
 },
 {
  "start": 1577.56,
  "end": 1583.44,
  "text": "if actually what we'd done to Tasmania, which was, you know, kind of take it over and through",
  "who": 2
 },
 {
  "start": 1583.44,
  "end": 1589.7199999999998,
  "text": "accident and design basically kill off the entire population? What if Martians arrived",
  "who": 2
 },
 {
  "start": 1589.72,
  "end": 1596.96,
  "text": "and did that to, well, the home counties and London? So there's like a gleeful portrait",
  "who": 2
 },
 {
  "start": 1596.96,
  "end": 1602.56,
  "text": "of all of these towns that the Wells had kind of lived in and been judged and disapproved",
  "who": 2
 },
 {
  "start": 1602.56,
  "end": 1607.88,
  "text": "of. So he systematically sets about destroying them with lasers because, you know, he's got",
  "who": 2
 },
 {
  "start": 1607.88,
  "end": 1612.7600000000002,
  "text": "this wonderful vision of destruction of all of these petty minded people. Very important",
  "who": 2
 },
 {
  "start": 1612.7600000000002,
  "end": 1618.8800000000003,
  "text": "there's a priest in there who can't accept the reality of this overthrow. And then the",
  "who": 2
 },
 {
  "start": 1618.8800000000003,
  "end": 1624.2000000000003,
  "text": "brilliant ending of that book is it's not the British ingenuity or engineers or science",
  "who": 2
 },
 {
  "start": 1624.2000000000003,
  "end": 1630.9400000000003,
  "text": "that wins. It's the fact that the Martians aren't protected from bacteria that killed",
  "who": 2
 },
 {
  "start": 1630.9400000000003,
  "end": 1638.2400000000002,
  "text": "them off. So it's nothing to do with us, nothing to do with humanity, it's to do with viruses",
  "who": 2
 },
 {
  "start": 1638.2400000000002,
  "end": 1644.0800000000002,
  "text": "and disease. And that's a sense of, again, another sort of switch, another really satirical",
  "who": 2
 },
 {
  "start": 1644.0800000000002,
  "end": 1650.4800000000005,
  "text": "subversion of British imperial power is what Wells is after at that point. It's a very",
  "who": 2
 },
 {
  "start": 1650.4800000000005,
  "end": 1653.2400000000002,
  "text": "brilliant book, I think.",
  "who": 2
 },
 {
  "start": 1653.24,
  "end": 1656.12,
  "text": "Still to come on the History Extra podcast.",
  "who": 0
 },
 {
  "start": 1656.12,
  "end": 1665.4,
  "text": "HG Wells predicted an atom bomb in 1914 and he thought it would emerge around about 1945.",
  "who": 2
 },
 {
  "start": 1665.4,
  "end": 1669.96,
  "text": "So that's kind of a fairly amazing kind of sense of what they were understanding about,",
  "who": 2
 },
 {
  "start": 1669.96,
  "end": 1674.96,
  "text": "you know, the projection into the future. You can release this extraordinary energy.",
  "who": 2
 },
 {
  "start": 1707.96,
  "end": 1711.96,
  "text": "We Norwegians take on average 1,748 pictures a year.",
  "who": 3
 },
 {
  "start": 1711.96,
  "end": 1714.96,
  "text": "Thousands of views are deleted if you lose your mobile phone.",
  "who": 3
 },
 {
  "start": 1714.96,
  "end": 1719.96,
  "text": "With private mobile subscription at Telenor you get MinSki included, which gives you safe",
  "who": 3
 },
 {
  "start": 1719.96,
  "end": 1722.96,
  "text": "and unlimited storage of all your pictures.",
  "who": 3
 },
 {
  "start": 1722.96,
  "end": 1725.96,
  "text": "MinSki, one of many included safety services.",
  "who": 3
 },
 {
  "start": 1730.85,
  "end": 1736.5833333333333,
  "text": "And it's interesting that it's not military might that defeats them, but it's science.",
  "who": 1,
  "matched": true
 },
 {
  "start": 1736.5833333333333,
  "end": 1738.583333333333,
  "text": "It's science in its purest form, I suppose.",
  "who": 2
 },
 {
  "start": 1737.35,
  "end": 1742.35,
  "text": "Yeah, or else it's biology, you know, because science doesn't kind of come into this really.",
  "who": 2,
  "matched": true
 },
 {
  "start": 1742.35,
  "end": 1748.35,
  "text": "I mean, the defences that humanity have against the Martians don't work at all.",
  "who": 2
 },
 {
  "start": 1748.35,
  "end": 1751.35,
  "text": "And they might think that they're at the height of scientific power, but actually it's the",
  "who": 2
 },
 {
  "start": 1751.35,
  "end": 1756.35,
  "text": "pure fact of biology. You know, if you come from somewhere else, then you're going to be",
  "who": 2
 },
 {
  "start": 1756.35,
  "end": 1761.35,
  "text": "susceptible to diseases. And this is what happens with settler colonialism.",
  "who": 2
 },
 {
  "start": 1761.35,
  "end": 1770.35,
  "text": "So it's why when you arrive in this virgin territory, so thought of in North America,",
  "who": 2
 },
 {
  "start": 1770.35,
  "end": 1774.35,
  "text": "that what you do basically is transmit all kinds of diseases that kill off the natives",
  "who": 2
 },
 {
  "start": 1774.35,
  "end": 1779.35,
  "text": "because they have no they built up no immunity to those kinds of things.",
  "who": 2
 },
 {
  "start": 1779.35,
  "end": 1784.35,
  "text": "So it's it's mass slaughter or purely by accident.",
  "who": 2
 },
 {
  "start": 1784.35,
  "end": 1788.35,
  "text": "And that's what the war of the worlds is also just neatly inverting.",
  "who": 2
 },
 {
  "start": 1788.35,
  "end": 1790.35,
  "text": "What if we were the object of that?",
  "who": 2
 },
 {
  "start": 1790.35,
  "end": 1795.35,
  "text": "What if someone brought us a disease or an illness that we have no immunity to?",
  "who": 2,
  "matched": true
 },
 {
  "start": 1795.35,
  "end": 1799.35,
  "text": "And we've also been living through that in the last two years, haven't we?",
  "who": 2
 },
 {
  "start": 1799.04,
  "end": 1802.44,
  "text": "Turning to search engine results, it's interesting.",
  "who": 1,
  "matched": true
 },
 {
  "start": 1802.96,
  "end": 1810.96,
  "text": "A huge portion of them are about three male American authors, all born in 1920.",
  "who": 1
 },
 {
  "start": 1810.98,
  "end": 1812.98,
  "text": "And I want to talk about them a bit.",
  "who": 1,
  "matched": true
 },
 {
  "start": 1812.98,
  "end": 1816.98,
  "text": "And then I also want to talk to you about whether it's a coincidence that they share those characteristics.",
  "who": 1
 },
 {
  "start": 1816.98,
  "end": 1820.98,
  "text": "So they're Isaac Asimov, Ray Bradbury and Frank Herbert.",
  "who": 1
 },
 {
  "start": 1820.98,
  "end": 1826.98,
  "text": "Agrobiodiverse on Twitter asks, who is the greatest English language science fiction writer?",
  "who": 1
 },
 {
  "start": 1826.98,
  "end": 1829.98,
  "text": "And why is it Isaac Asimov?",
  "who": 1
 },
 {
  "start": 1829.98,
  "end": 1832.98,
  "text": "That's the kind of the tone.",
  "who": 1
 },
 {
  "start": 1832.98,
  "end": 1839.98,
  "text": "I wanted to talk to you about why the ideas of these three men have proven so powerful and so long lasting, I suppose.",
  "who": 1
 },
 {
  "start": 1839.96,
  "end": 1849.96,
  "text": "Yes. So I think the the shift comes from H.G. Wells and the English or British scientific romance, which is, you know,",
  "who": 2
 },
 {
  "start": 1849.96,
  "end": 1853.96,
  "text": "it develops in the 1890s and gets very kind of fixed quite quickly.",
  "who": 2
 },
 {
  "start": 1853.96,
  "end": 1857.96,
  "text": "And you can see Arthur C. Clarke actually is at the end of that tradition as well.",
  "who": 2
 },
 {
  "start": 1857.96,
  "end": 1860.96,
  "text": "He was someone who was kind of directly influenced by Wells.",
  "who": 2
 },
 {
  "start": 1860.96,
  "end": 1869.96,
  "text": "So there's kind of a continuity there. But what happens in the 1920s is a very specific set of circumstances in America,",
  "who": 2
 },
 {
  "start": 1869.96,
  "end": 1873.96,
  "text": "which which develop these pulp magazines.",
  "who": 2
 },
 {
  "start": 1873.96,
  "end": 1879.96,
  "text": "So it's Hugo Gernsback who is a guy who publishes.",
  "who": 2
 },
 {
  "start": 1879.96,
  "end": 1881.96,
  "text": "He's an entrepreneur in radio technology.",
  "who": 2
 },
 {
  "start": 1881.96,
  "end": 1887.96,
  "text": "So this is the beginning of people building their home radios and communicating with each other, which is very big in America.",
  "who": 2
 },
 {
  "start": 1887.96,
  "end": 1890.96,
  "text": "CB radio, all that sort of stuff.",
  "who": 2
 },
 {
  "start": 1890.96,
  "end": 1892.96,
  "text": "He develops all of these kind of pulp magazines around that.",
  "who": 2
 },
 {
  "start": 1892.96,
  "end": 1900.96,
  "text": "And then he just starts adding fiction in, but then realizes that all he can do is just is just reprint old H.G. Wells stories.",
  "who": 2
 },
 {
  "start": 1900.96,
  "end": 1905.96,
  "text": "So then he starts trying to commission new things to come through.",
  "who": 2
 },
 {
  "start": 1905.96,
  "end": 1908.96,
  "text": "And that's where science fiction is named. That's where it comes from.",
  "who": 2
 },
 {
  "start": 1908.96,
  "end": 1918.96,
  "text": "And in 1929, you get Astounding Science Fiction, which is often considered to be the home of American engineer hard science fiction.",
  "who": 2
 },
 {
  "start": 1918.96,
  "end": 1926.96,
  "text": "So this sort of extrapolative idea. So it's very important that people writing in that have a kind of authority training in science.",
  "who": 2
 },
 {
  "start": 1926.96,
  "end": 1930.96,
  "text": "And that's certainly what Asimov has, who was a chemist.",
  "who": 2
 },
 {
  "start": 1931.43,
  "end": 1934.4300000000003,
  "text": "And I mean, Frank Herbert's mind was extraordinary.",
  "who": 2,
  "matched": true
 },
 {
  "start": 1934.4300000000003,
  "end": 1939.4300000000003,
  "text": "But he was really interested in ecology and biology and science.",
  "who": 2
 },
 {
  "start": 1939.4300000000003,
  "end": 1946.4300000000003,
  "text": "Ray Bradbury, bit more of a kind of fantasy crossover figure, softer science fiction.",
  "who": 2
 },
 {
  "start": 1946.4300000000003,
  "end": 1951.4300000000003,
  "text": "He was not so keen on hard, extrapolative kind of science fiction.",
  "who": 2
 },
 {
  "start": 1951.4300000000003,
  "end": 1959.4300000000003,
  "text": "And in the 1930s, there is just simply a place for people like that to publish an awful lot of stuff and kind of grow up in public, really.",
  "who": 2
 },
 {
  "start": 1959.4300000000003,
  "end": 1968.4300000000003,
  "text": "And it's very unusual community in that they have very active letters pages and the letter writers themselves become writers.",
  "who": 2
 },
 {
  "start": 1968.4300000000003,
  "end": 1973.4300000000003,
  "text": "So this is quite often how people kind of start, is that they move into these kind of areas.",
  "who": 2
 },
 {
  "start": 1973.4300000000003,
  "end": 1979.4300000000003,
  "text": "And then another figure, I would add, who's probably more important than all of those three, I would say,",
  "who": 2
 },
 {
  "start": 1979.4300000000003,
  "end": 1990.4300000000003,
  "text": "controversially, is Robert Heinlein, who was also trained scientist and worked as an engineer in the war for the Navy.",
  "who": 2
 },
 {
  "start": 1990.4300000000003,
  "end": 1995.4300000000003,
  "text": "He'd been in the Navy and a standing science fiction editor.",
  "who": 2
 },
 {
  "start": 1995.4300000000003,
  "end": 2005.4300000000003,
  "text": "John Campbell was someone who was also trained in science and was very strict about the rules of what what what science fiction kind of could do.",
  "who": 2
 },
 {
  "start": 2005.4300000000003,
  "end": 2011.4300000000003,
  "text": "So I think there's a whole cluster here that makes American science fiction in the 20s and 30s really specific.",
  "who": 2
 },
 {
  "start": 2011.53,
  "end": 2014.6633333333334,
  "text": "And that's where those key figures emerge from.",
  "who": 2,
  "matched": true
 },
 {
  "start": 2014.96,
  "end": 2017.96,
  "text": "Was that Heinlein who wrote Starship Troopers?",
  "who": 1
 },
 {
  "start": 2018.53,
  "end": 2019.7966666666666,
  "text": "Yeah, that's right.",
  "who": 2,
  "matched": true
 },
 {
  "start": 2019.96,
  "end": 2033.96,
  "text": "So Robert Heinlein was really crucial in a way for a postwar shift, which was that he started out in magazines and pulp magazines and wrote quite a lot of short stories.",
  "who": 2
 },
 {
  "start": 2033.96,
  "end": 2042.96,
  "text": "But in the immediate post 1945 period, he was the first science fiction writer to kind of get a book deal with a major mainstream publisher.",
  "who": 2
 },
 {
  "start": 2044.05,
  "end": 2049.05,
  "text": "And that changes the whole nature of where science fiction is published in America.",
  "who": 2,
  "matched": true
 },
 {
  "start": 2049.05,
  "end": 2055.05,
  "text": "It moves from magazines, pulp magazines to paperbacks and that sort of mass selling of paperbacks.",
  "who": 2
 },
 {
  "start": 2055.05,
  "end": 2063.05,
  "text": "And Heinlein was the first person really in this genre, which was very low and very minor and considered not at all important.",
  "who": 2
 },
 {
  "start": 2063.05,
  "end": 2069.05,
  "text": "He was making money out of this. He was making a very, very good living indeed out of this kind of stuff.",
  "who": 2
 },
 {
  "start": 2069.05,
  "end": 2078.05,
  "text": "And he also targeted young adult readers, as we would now call it, a whole series of books focused around young protagonists and so on.",
  "who": 2
 },
 {
  "start": 2078.05,
  "end": 2086.05,
  "text": "So he was very influential. He was also fabulously right wing and Starship Troopers, which came out in 1959.",
  "who": 2
 },
 {
  "start": 2086.05,
  "end": 2098.05,
  "text": "It's a brilliant film version by Paul Verhoeven. I always recommend. It's so funny. But that is a very divisive book because it kind of argues that America should be a militaristic society.",
  "who": 2
 },
 {
  "start": 2098.05,
  "end": 2104.05,
  "text": "Everyone should go through military training. You can't vote unless you've been been in the army and done your service.",
  "who": 2
 },
 {
  "start": 2104.05,
  "end": 2111.05,
  "text": "You know, that sort of thing. And you must relentlessly attack all alien life forms, which are a threat to your dominance.",
  "who": 2
 },
 {
  "start": 2111.05,
  "end": 2125.05,
  "text": "You know, so it's a very kind of strong politically from the right. And you get someone like Ray Bradbury, who's much more identified with a kind of softer left, a liberal kind of approach to these sort of things, writes very mournfully about the nuclear age.",
  "who": 2
 },
 {
  "start": 2125.05,
  "end": 2139.05,
  "text": "The Martian Chronicles is a wonderful book from 1950, which is like the opposite of Heinlein, really anti militaristic, very, very sort of full of melancholy about imperialism and colonialism.",
  "who": 2
 },
 {
  "start": 2139.05,
  "end": 2145.05,
  "text": "The Martians are dying off, you know, as the Americans arrive on Mars, that sort of sense of the politics of that.",
  "who": 2
 },
 {
  "start": 2145.05,
  "end": 2162.05,
  "text": "So you get the whole array there. And Frank Herbert's June coming in the 1960s is that major blockbuster, which again is very in front of its time, really thinking about ecology and precarious sand desert kind of cultures.",
  "who": 2
 },
 {
  "start": 2162.05,
  "end": 2172.05,
  "text": "He was someone who was very interested in experimental farming in extreme conditions. And he imagined all of this sort of stuff on the planets of Arrakis.",
  "who": 2
 },
 {
  "start": 2172.05,
  "end": 2182.05,
  "text": "You know, this sort of sense of a whole culture, but a desert culture inside that. So they're all very informed by science, but science doesn't give you politics.",
  "who": 2
 },
 {
  "start": 2182.05,
  "end": 2190.05,
  "text": "Politics comes from how you how you work with science and technology. So you get either a Heinlein or you get Bradbury.",
  "who": 2
 },
 {
  "start": 2189.01,
  "end": 2195.01,
  "text": "I wanted to talk to you about a few other authors that haven't come up on Google searches, but who I think might tell us something.",
  "who": 1,
  "matched": true
 },
 {
  "start": 2195.01,
  "end": 2207.01,
  "text": "One of them who I think also falls into that trend of writing about ecology and environment is Ursula Le Guin. What were her sort of key ideas and concerns and influence, I suppose?",
  "who": 1
 },
 {
  "start": 2206.96,
  "end": 2223.96,
  "text": "Yes. So finally, we get to talk about a woman author. Amazing. And Ursula Le Guin is very important in the emergence of a kind of much more overtly feminist science fiction, which is not to say women were not around.",
  "who": 2
 },
 {
  "start": 2223.96,
  "end": 2228.96,
  "text": "You know, there were women writing all the way through from the beginning of science fiction.",
  "who": 2
 },
 {
  "start": 2228.96,
  "end": 2240.96,
  "text": "The first most significant utopia is Margaret Cavendish going all the way back to the blazing world in the 17th century. And you do get women writers who write really good science fiction in the late 19th century alongside Wells.",
  "who": 2
 },
 {
  "start": 2240.96,
  "end": 2246.96,
  "text": "But Ursula Le Guin is a really significant figure in the 60s. And I think her background is really interesting.",
  "who": 2
 },
 {
  "start": 2246.96,
  "end": 2257.96,
  "text": "So both of her parents were anthropologists and she was brought up in in a very kind of rich university context where she was exposed to lots of really interesting ideas.",
  "who": 2
 },
 {
  "start": 2257.96,
  "end": 2265.96,
  "text": "And so her fiction is quite often driven by what it means to encounter alien cultures, what it means to encounter the other.",
  "who": 2
 },
 {
  "start": 2265.96,
  "end": 2274.96,
  "text": "And her view is not one of search and destroy or everything that is different from you. But what would it be like?",
  "who": 2
 },
 {
  "start": 2274.96,
  "end": 2279.96,
  "text": "How would you try and deal with a completely alien culture?",
  "who": 2
 },
 {
  "start": 2279.96,
  "end": 2293.96,
  "text": "So, you know, one of her key books is The Left Hand of Darkness, and she's very interested in exploring kind of alternate universes.",
  "who": 2
 },
 {
  "start": 2293.96,
  "end": 2301.96,
  "text": "What does it mean when you encounter someone who can change gender at different points in their life?",
  "who": 2
 },
 {
  "start": 2301.96,
  "end": 2308.96,
  "text": "What would that do to your whole kind of system of belief and thought? It completely throws the narrator in quite interesting ways.",
  "who": 2
 },
 {
  "start": 2308.96,
  "end": 2314.96,
  "text": "So she's very interested in the anthropology of that sort of stuff. And she's also quite early on.",
  "who": 2
 },
 {
  "start": 2314.96,
  "end": 2326.96,
  "text": "I mean, the understanding of ecology and the damage being done to the ecologies of fragile ecologies of the Earth was beginning to emerge in the 1960s.",
  "who": 2
 },
 {
  "start": 2326.96,
  "end": 2330.96,
  "text": "This is all quite very early kind of stuff. But she was very interested in that.",
  "who": 2
 },
 {
  "start": 2330.96,
  "end": 2346.96,
  "text": "So maybe native cultures that you encounter have a different relationship to nature. It's not seen as a resource to be used and consumed, but that you live with in totally different ways.",
  "who": 2
 },
 {
  "start": 2346.96,
  "end": 2358.96,
  "text": "And that has been hugely influential, too. So she's a kind of very, again, soft science fiction, liberal end, interested in intellectual, social ideas, sociology and anthropology.",
  "who": 2
 },
 {
  "start": 2358.96,
  "end": 2365.96,
  "text": "The kind of stuff that, say, Asimov or Heinlein are less interested in, although they have many things to say about it.",
  "who": 2
 },
 {
  "start": 2365.96,
  "end": 2373.96,
  "text": "Her focus is not on hard technology necessarily, but on these ideas of encounter, I think. So she's crucial.",
  "who": 2
 },
 {
  "start": 2373.96,
  "end": 2381.96,
  "text": "Another figure is Saniswap Lem, who is Polish, I believe. What were his concerns and ideas?",
  "who": 1
 },
 {
  "start": 2381.96,
  "end": 2387.96,
  "text": "And what do they tell us about that point, I suppose, in European and international history?",
  "who": 1
 },
 {
  "start": 2387.96,
  "end": 2392.96,
  "text": "Yeah, it's so important to and I hope we can say more about this towards the end.",
  "who": 2
 },
 {
  "start": 2392.96,
  "end": 2398.96,
  "text": "But it's so important to have a kind of international or multinational perspective for science fiction.",
  "who": 2
 },
 {
  "start": 2399.03,
  "end": 2406.0299999999997,
  "text": "So we're beginning to understand that although we've had this endless argument about is HG Wells the father of science fiction?",
  "who": 2,
  "matched": true
 },
 {
  "start": 2406.0299999999997,
  "end": 2414.0299999999997,
  "text": "Actually, there are lots of traditions that are emerging around about the same time in many different kind of nations.",
  "who": 2
 },
 {
  "start": 2414.0299999999997,
  "end": 2424.0299999999997,
  "text": "And so there is a kind of tradition in Russian writing and Soviet Union writing, which of course is very interested in utopia.",
  "who": 2
 },
 {
  "start": 2424.0299999999997,
  "end": 2429.0299999999997,
  "text": "In fact, the Bolsheviks who drove the revolution wrote science fiction.",
  "who": 2
 },
 {
  "start": 2429.0299999999997,
  "end": 2434.0299999999997,
  "text": "They wrote utopian kind of science fiction, some of them quite explicitly.",
  "who": 2
 },
 {
  "start": 2434.0299999999997,
  "end": 2439.0299999999997,
  "text": "And, you know, we're very interested in the politics of that, of projecting futures.",
  "who": 2
 },
 {
  "start": 2439.0299999999997,
  "end": 2443.0299999999997,
  "text": "They were very interested in futurism, those sorts of ideas.",
  "who": 2
 },
 {
  "start": 2443.0299999999997,
  "end": 2452.0299999999997,
  "text": "By the time you get someone like Stanislav Lem, who is writing in what was then a satellite communist state.",
  "who": 2
 },
 {
  "start": 2452.0299999999997,
  "end": 2460.0299999999997,
  "text": "So part of the part of the whole Soviet Union alliance in the East during the Cold War.",
  "who": 2
 },
 {
  "start": 2460.0299999999997,
  "end": 2464.0299999999993,
  "text": "He's got a slightly different relationship to science fiction.",
  "who": 2,
  "matched": true
 },
 {
  "start": 2464.0299999999993,
  "end": 2469.0299999999997,
  "text": "So the virtue of it is that it can be allegorical.",
  "who": 2
 },
 {
  "start": 2469.0299999999997,
  "end": 2477.0299999999997,
  "text": "That is, you can write about the state that you're in without directly criticising the state, because as soon as you do, your work gets suppressed.",
  "who": 2
 },
 {
  "start": 2477.0299999999997,
  "end": 2487.0299999999997,
  "text": "So science fiction becomes a very kind of powerful device or a genre in which you can displace your criticism and begin to kind of target some concerns.",
  "who": 2
 },
 {
  "start": 2487.0299999999997,
  "end": 2494.0299999999997,
  "text": "So I think he's important for that. He's very interested in science and technology, but also has this sort of softer edge.",
  "who": 2
 },
 {
  "start": 2494.0299999999997,
  "end": 2503.0299999999997,
  "text": "So if you read Solaris, which has been filmed twice, both times brilliantly, but very differently.",
  "who": 2
 },
 {
  "start": 2503.0299999999997,
  "end": 2511.0299999999997,
  "text": "That's about a bunch of scientists who are sent to a planet to try and communicate with what seems to be a planetary consciousness.",
  "who": 2
 },
 {
  "start": 2511.0299999999997,
  "end": 2516.0299999999997,
  "text": "And it's communicating in a completely different way from from language.",
  "who": 2
 },
 {
  "start": 2516.0299999999997,
  "end": 2521.0299999999997,
  "text": "It kind of extracts your worst memory from your mind and kind of beams it back at you.",
  "who": 2
 },
 {
  "start": 2521.0299999999997,
  "end": 2526.0299999999997,
  "text": "And is there any possibility of communicating with this absolute other?",
  "who": 2
 },
 {
  "start": 2526.0299999999997,
  "end": 2530.0299999999997,
  "text": "So that's a really interesting, crucial kind of story.",
  "who": 2
 },
 {
  "start": 2530.0299999999997,
  "end": 2542.0299999999997,
  "text": "And there are many figures like Lem who kind of right on the edge of censorship and being suppressed by by Communist Party state who don't like this stuff.",
  "who": 2
 },
 {
  "start": 2542.0299999999997,
  "end": 2549.0299999999997,
  "text": "They don't they don't want this kind of material. They want happy tractor driver kind of realist material.",
  "who": 2
 },
 {
  "start": 2549.0299999999997,
  "end": 2553.0299999999997,
  "text": "So they're kind of treated with suspicion on the edge of this.",
  "who": 2
 },
 {
  "start": 2553.0299999999997,
  "end": 2560.0299999999997,
  "text": "And it makes their work really intriguing. And you have to interpret quite hard what it is that they might be getting at.",
  "who": 2
 },
 {
  "start": 2560.0299999999997,
  "end": 2573.0299999999997,
  "text": "So that's true also of say this Drogatsky brothers who wrote Roadside Picnic, which became Stalker, a film by Tarkovsky.",
  "who": 2
 },
 {
  "start": 2573.0299999999997,
  "end": 2585.0299999999997,
  "text": "And it's a very influential story because it's about alien technology that no one understands that you sort of pick up and it either does wondrous things to you or it kills you or it mutates you.",
  "who": 2
 },
 {
  "start": 2585.0299999999997,
  "end": 2593.0299999999997,
  "text": "And no one quite understands what it is. But that was a book that was suppressed as somehow in some way critical.",
  "who": 2
 },
 {
  "start": 2593.0299999999997,
  "end": 2597.0299999999997,
  "text": "We're not sure how, but we would like to ban and censor this anyway.",
  "who": 2
 },
 {
  "start": 2597.0299999999997,
  "end": 2608.0299999999997,
  "text": "So that sense of how you might use science fiction again in a sort of political context as a sort of way of displacing criticism is very important.",
  "who": 2
 },
 {
  "start": 2607.96,
  "end": 2616.96,
  "text": "Spaghetti Tree on Twitter wants to know about the impacts of the early Cold War in that transitional period where science began to truly influence literature.",
  "who": 1
 },
 {
  "start": 2616.96,
  "end": 2621.96,
  "text": "Is there something about the Cold War that we can say more generally about science fiction and history?",
  "who": 1
 },
 {
  "start": 2621.96,
  "end": 2632.96,
  "text": "Yeah, that is a really good question. And I do think, you know, so I've written a history of science fiction, which I hinge around 1945 because I think 1945 is an absolutely crucial moment.",
  "who": 2
 },
 {
  "start": 2632.96,
  "end": 2642.96,
  "text": "That's when we get the atom bomb being used. That is the first super weapon that's been imagined for so many decades by science fiction actually realised.",
  "who": 2
 },
 {
  "start": 2642.96,
  "end": 2651.96,
  "text": "HG Wells predicted an atom bomb in 1914 and he thought it would emerge around about 1945.",
  "who": 2
 },
 {
  "start": 2651.96,
  "end": 2658.96,
  "text": "So that's kind of a fairly amazing kind of sense of what they were understanding about, you know, the projection into the future.",
  "who": 2
 },
 {
  "start": 2658.96,
  "end": 2671.96,
  "text": "You can release this extraordinary energy. But what that of course produced was these absolutely implacably opposed blocks between West and East, the Soviet Union and its communist allies.",
  "who": 2
 },
 {
  "start": 2671.96,
  "end": 2680.96,
  "text": "Versus America and its capitalist allies. And you get lots of science fiction, which is either utterly dystopian.",
  "who": 2
 },
 {
  "start": 2680.96,
  "end": 2689.96,
  "text": "So imagining nuclear meltdowns of various kinds or survival of nuclear catastrophe in various kinds of ways.",
  "who": 2
 },
 {
  "start": 2689.96,
  "end": 2696.96,
  "text": "But you also get a sort of drive to try and think beyond these political divisions.",
  "who": 2
 },
 {
  "start": 2696.96,
  "end": 2706.96,
  "text": "That's actually what Arthur C. Clarke's most transcendent work is about, is he's always saying we need to leave behind human division and these political kind of shifts.",
  "who": 2
 },
 {
  "start": 2706.96,
  "end": 2715.96,
  "text": "And it's only science, it's only space travel moving outwards that can allow us to transcend this, which is why his visions are so sort of ecstatic.",
  "who": 2
 },
 {
  "start": 2715.96,
  "end": 2724.96,
  "text": "You know, the end of 2001, whatever the hell that means, is a sort of vision of transcendence of these kinds of political moments.",
  "who": 2
 },
 {
  "start": 2724.96,
  "end": 2737.96,
  "text": "So the Cold War is really, really very important. And you get someone like Robert Heinen again, who works out the kind of logic of mutually assured destruction.",
  "who": 2
 },
 {
  "start": 2737.96,
  "end": 2742.96,
  "text": "That is, you know, we've got a bomb. If you set yours off, we'll set ours off. Everyone, everything ends.",
  "who": 2
 },
 {
  "start": 2742.96,
  "end": 2747.96,
  "text": "So it's a kind of, you know, a stalemate. He works out that logic in the middle of the Second World War.",
  "who": 2
 },
 {
  "start": 2748.15,
  "end": 2753.1500000000005,
  "text": "You know, that's a sense of right before all the politicians have got there.",
  "who": 2,
  "matched": true
 },
 {
  "start": 2753.1500000000005,
  "end": 2758.1500000000005,
  "text": "An American writer like Judith Merrill takes a very different view of this.",
  "who": 2
 },
 {
  "start": 2758.1500000000005,
  "end": 2767.1500000000005,
  "text": "So, you know, what's the effect of this on mothers, on motherhood? What if you produce your mutant children? What's going to happen about that?",
  "who": 2
 },
 {
  "start": 2767.1500000000005,
  "end": 2782.1500000000005,
  "text": "Octavia Butler, another really important writer emerging in the 1970s, is sort of saying that humanity is kind of doomed with this kind of violence and constant drive to domination.",
  "who": 2
 },
 {
  "start": 2782.1500000000005,
  "end": 2789.1500000000005,
  "text": "So we actually need to actively embrace the alien other and become something else, move beyond our division.",
  "who": 2
 },
 {
  "start": 2789.1500000000005,
  "end": 2793.6166666666677,
  "text": "And that is also, I mean, hers is driven by a question around race.",
  "who": 2,
  "matched": true
 },
 {
  "start": 2793.96,
  "end": 2803.96,
  "text": "She was one of the earliest black women science fiction writers. But it's also clearly a Cold War logic as well of let's just move beyond this kind of division.",
  "who": 2
 },
 {
  "start": 2803.96,
  "end": 2817.96,
  "text": "And you get really weird things happening so that in 1980s, some some listeners might remember that Ronald Reagan had this whole project called Star Wars, which was, you know, to kind of put a defence system in space.",
  "who": 2
 },
 {
  "start": 2817.96,
  "end": 2821.96,
  "text": "That was written for him by a group of science fiction writers.",
  "who": 2
 },
 {
  "start": 2821.96,
  "end": 2830.96,
  "text": "Robert Heinlein, Greg Bear were heavily involved in that. They wrote a report out of their science fiction, which then became government policy.",
  "who": 2
 },
 {
  "start": 2830.96,
  "end": 2834.96,
  "text": "You know, it's extraordinary the influence that those science fiction writers had.",
  "who": 2
 },
 {
  "start": 2834.96,
  "end": 2842.96,
  "text": "They were all very politically motivated to help the Republican Party and to, in a sense, extend the Cold War into space itself.",
  "who": 2
 },
 {
  "start": 2842.96,
  "end": 2850.96,
  "text": "And so, you know, this vision perhaps didn't work because it was science fiction. But nevertheless, it got billions of dollars. It's amazing.",
  "who": 2
 },
 {
  "start": 2851.68,
  "end": 2856.6799999999994,
  "text": "That leads nicely, actually, talking about the ideas in which science fiction has influenced reality.",
  "who": 1,
  "matched": true
 },
 {
  "start": 2856.6799999999994,
  "end": 2869.6799999999994,
  "text": "N.P. Ryan on Twitter asks, Is it right to say that Churchill's initial fear that Londoners wouldn't come back out of underground stations if allowed to shelter from bombs in them came from the time machine, the H.G. Wells story?",
  "who": 1
 },
 {
  "start": 2869.6799999999994,
  "end": 2872.6799999999994,
  "text": "Do you know whether that's true or not?",
  "who": 1
 },
 {
  "start": 2871.94,
  "end": 2874.9399999999996,
  "text": "I can't answer whether it's specifically true or not.",
  "who": 2,
  "matched": true
 },
 {
  "start": 2874.96,
  "end": 2885.96,
  "text": "But I think there is that that was certainly the view was that if people were allowed to go into the underground system, then they would never come out.",
  "who": 2
 },
 {
  "start": 2885.96,
  "end": 2889.96,
  "text": "And the kind of the economy would sort of collapse. So there was a genuine kind of fear about that.",
  "who": 2
 },
 {
  "start": 2889.96,
  "end": 2898.96,
  "text": "There is a sort of imagination of science fiction, which is kind of bubbling around, which has these visions of underground living, which become even stronger in the Cold War.",
  "who": 2
 },
 {
  "start": 2898.96,
  "end": 2915.96,
  "text": "So bunker living and this idea of we all ending up in bunkers. There's a great novel by Philip K. Dick, the 1950s American writer, called The Penultimate Truth, which is where humanity has basically been for decades living in bunkers underground,",
  "who": 2
 },
 {
  "start": 2915.96,
  "end": 2925.96,
  "text": "watching news feeds of robots fighting a war on the surface. And they discover that the robots are just simply making films and that there has been no war for decades.",
  "who": 2
 },
 {
  "start": 2925.96,
  "end": 2930.96,
  "text": "And they've all been tricked into this kind of system by artificial intelligences.",
  "who": 2
 },
 {
  "start": 2930.96,
  "end": 2936.96,
  "text": "So, you know, there is a sense of a of a bunker kind of imagination to science fiction.",
  "who": 2
 },
 {
  "start": 2936.96,
  "end": 2940.96,
  "text": "So maybe Churchill was picking up on that. He did read absolutely everything.",
  "who": 2
 },
 {
  "start": 2940.96,
  "end": 2950.96,
  "text": "We should return to the idea that you mentioned earlier about other traditions or other voices that haven't been given, perhaps the recognition that they might otherwise deserve.",
  "who": 1
 },
 {
  "start": 2951.22,
  "end": 2955.4599999999996,
  "text": "Who should we champion? Who should we highlight that we haven't already talked about in this conversation?",
  "who": 1,
  "matched": true
 },
 {
  "start": 2954.96,
  "end": 2960.96,
  "text": "Yeah. So, I mean, I think there are many. It's a golden age right now. It's a golden age of science fiction.",
  "who": 2
 },
 {
  "start": 2960.96,
  "end": 2967.96,
  "text": "Really, there's so much extraordinary work. But I think what's extraordinary about it is this explosion across the whole globe.",
  "who": 2
 },
 {
  "start": 2967.96,
  "end": 2974.96,
  "text": "So it's now impossible for someone like me to sit here and say, I've read everything in science fiction.",
  "who": 2
 },
 {
  "start": 2974.96,
  "end": 2980.96,
  "text": "You might have been able to do that maybe in 1950 and it's becoming very difficult.",
  "who": 2
 },
 {
  "start": 2980.96,
  "end": 2988.96,
  "text": "But now it's simply impossible. And we need kind of experts. There's a whole Indian kind of science fiction world.",
  "who": 2
 },
 {
  "start": 2988.96,
  "end": 2995.96,
  "text": "There's a whole African science fiction, lots of different kind of countries producing lots of different kinds of work.",
  "who": 2
 },
 {
  "start": 2995.96,
  "end": 3005.96,
  "text": "I've just been reading The Old Drift by Namwali Serpal, which won the best science fiction novel, Arthur C. Clarke Award in 2020.",
  "who": 2
 },
 {
  "start": 3005.96,
  "end": 3015.96,
  "text": "And that's set in Zambia. And you just think, is this a science fiction novel? And it slowly, carefully does take you into a science fictional world in a really clever, ingenious kind of way.",
  "who": 2
 },
 {
  "start": 3015.96,
  "end": 3021.96,
  "text": "And it feels very significant, vital, important kind of work that's being done.",
  "who": 2
 },
 {
  "start": 3021.96,
  "end": 3027.96,
  "text": "There's a thing called Gulf Futurism, which is a kind of science fiction that's emerging from the Middle East.",
  "who": 2
 },
 {
  "start": 3027.96,
  "end": 3041.96,
  "text": "So Frankenstein in Baghdad, amazing book by Ahmed Sadawi, which reimagines the monster in the middle of the Iraq war.",
  "who": 2
 },
 {
  "start": 3041.96,
  "end": 3048.96,
  "text": "This is a monster put together from the body parts of people who've been blown up in the explosive, in explosions.",
  "who": 2
 },
 {
  "start": 3048.96,
  "end": 3056.96,
  "text": "And it kind of enacts the revenge of all the people who've been killed. It feels like a completely new, brilliant world of invention.",
  "who": 2
 },
 {
  "start": 3056.96,
  "end": 3070.96,
  "text": "So there's loads of stuff that's going on. And if people are able to get to London in October, there is a whole massive exhibition called Science Fiction at the Science Museum, which is trying to explore these ideas.",
  "who": 2
 },
 {
  "start": 3070.96,
  "end": 3077.96,
  "text": "I was involved in the development of that over the last five years, and they've been really committed to this idea of a global vision.",
  "who": 2
 },
 {
  "start": 3078.3,
  "end": 3082.3,
  "text": "So there's a quick way of doing that. It's going to be a great exhibition.",
  "who": 2,
  "matched": true
 },
 {
  "start": 3081.96,
  "end": 3090.96,
  "text": "Thank you so much. I wanted to end with just a few quick questions. We've had LDOP Exeter asks, what sci fi tropes have we achieved?",
  "who": 1
 },
 {
  "start": 3090.96,
  "end": 3099.96,
  "text": "And they suggest sliding doors, data pads, medical scans. And what have we missed? Hoverboard, Soylent Green. I mean, some of them I'd argue it's a good thing we've missed.",
  "who": 1
 },
 {
  "start": 3099.96,
  "end": 3108.96,
  "text": "Is there something we can say about the shape that history has taken compared to the shape that science fiction offered? Or is that too impossible?",
  "who": 1
 },
 {
  "start": 3108.96,
  "end": 3116.96,
  "text": "Yeah, I mean, I think it's a really good question. It's a perennial question as well. So should you measure science fiction by, you know, what it accurately predicts?",
  "who": 2
 },
 {
  "start": 3116.96,
  "end": 3129.96,
  "text": "And there is a there's a there's a famous book and phrase which is, you know, where's my jet board dude or whatever it was called, you know, that that sense of where's my where is all of this promise of this technology?",
  "who": 2
 },
 {
  "start": 3129.96,
  "end": 3139.96,
  "text": "It hasn't arrived. So these but they're sometimes called retro futures. This idea that, you know, back in the 50s, everything we didn't need food anymore. We just have a pill and it would be great.",
  "who": 2
 },
 {
  "start": 3139.96,
  "end": 3146.96,
  "text": "Or there'd be no work. You know, labor would be kind of ended and we'd all just lie around in hammocks and order around robots.",
  "who": 2
 },
 {
  "start": 3146.96,
  "end": 3158.96,
  "text": "And that hasn't happened. But on the other hand, I think it's much more interesting to look at how certain kind of imagination and explorations of technology have slowly kind of arrived.",
  "who": 2
 },
 {
  "start": 3158.96,
  "end": 3166.96,
  "text": "So many people say that the the mobile phone in America has this very different flip kind of device, doesn't it?",
  "who": 2
 },
 {
  "start": 3166.96,
  "end": 3173.96,
  "text": "So you kind of often open it out. And that's all because of Star Trek. So, you know, it needed to be like the communicators in in Star Trek.",
  "who": 2
 },
 {
  "start": 3173.96,
  "end": 3182.96,
  "text": "If you read Arthur C. Clarke on the future of computing in the 1960s, so he'd already predicted satellites.",
  "who": 2
 },
 {
  "start": 3182.96,
  "end": 3191.96,
  "text": "And then he said, well, I think we're going to basically in the future have a handheld kind of device, a computer where you can watch television.",
  "who": 2
 },
 {
  "start": 3191.96,
  "end": 3197.96,
  "text": "You can communicate with your friends. It would be, you know, by by vision and sound.",
  "who": 2
 },
 {
  "start": 3197.96,
  "end": 3206.96,
  "text": "You wouldn't need to worry about telephones anymore. And he's describing and also describing the shape when you see him on TV in the 60s of an iPad.",
  "who": 2
 },
 {
  "start": 3206.96,
  "end": 3218.96,
  "text": "And it's kind of fairly extraordinary that you can do that. People sometimes go to the kind of work of, say, James Cameron, a filmmaker, director who did Avatar,",
  "who": 2
 },
 {
  "start": 3218.96,
  "end": 3230.96,
  "text": "but also Steven Spielberg, who in his science fictions kind of he hires futurologists in order to try and just kind of tilt things slightly into the future.",
  "who": 2
 },
 {
  "start": 3230.96,
  "end": 3239.96,
  "text": "So, you know, their films are predicting, well, they create new technology. That's why James Cameron takes so long to produce a film is he has to invent a camera to film it.",
  "who": 2
 },
 {
  "start": 3239.96,
  "end": 3247.96,
  "text": "But in Spielberg's case, you know, iris recognition, all that sort of stuff is going on in his kind of films.",
  "who": 2
 },
 {
  "start": 3247.96,
  "end": 3259.96,
  "text": "And, you know, these these personal ads which kind of pick up your as you walk along the street, they sort of pick up your signature and direct personal ads at you.",
  "who": 2
 },
 {
  "start": 3259.96,
  "end": 3266.96,
  "text": "We've all been freaked out by what Instagram can do to you when it can really predict your desires in quite extraordinary ways.",
  "who": 2
 },
 {
  "start": 3266.96,
  "end": 3270.96,
  "text": "So that sort of sense of that artificial intelligence has obviously has been a kind of key idea.",
  "who": 2
 },
 {
  "start": 3270.96,
  "end": 3279.96,
  "text": "And people are are we on the edge of what's called the technological singularity, which is where machines become conscious.",
  "who": 2
 },
 {
  "start": 3279.96,
  "end": 3287.96,
  "text": "Even just a couple of months ago, someone in Google said, wait a minute, I think this I think my computer's just got just got sentient.",
  "who": 2
 },
 {
  "start": 3287.96,
  "end": 3297.96,
  "text": "And he was probably moved from his job. But actually, that idea of we're right on the edge of this kind of development is is is partly due to science fiction,",
  "who": 2
 },
 {
  "start": 3297.96,
  "end": 3308.96,
  "text": "partly due to science fiction being so fluid now with advanced technology companies, startup companies, you know, tech kind of stuff.",
  "who": 2
 },
 {
  "start": 3308.96,
  "end": 3320.96,
  "text": "We all look to Elon Musk, who's doing research into telepathy effectively and also extended life research, which is massive in the Silicon Valley.",
  "who": 2
 },
 {
  "start": 3320.96,
  "end": 3327.96,
  "text": "You know, will Walt Disney's head that's been frozen allegedly be reanimated?",
  "who": 2
 },
 {
  "start": 3327.96,
  "end": 3330.96,
  "text": "His family repeatedly deny that his head is frozen, by the way.",
  "who": 2
 },
 {
  "start": 3330.96,
  "end": 3339.96,
  "text": "And, you know, that sort of culture of can we escape the bounds of the human itself? It feels very kind of vibrant.",
  "who": 2
 },
 {
  "start": 3339.96,
  "end": 3347.96,
  "text": "And that's for me why science fiction is so vital now is there's a sense of all the technology is accelerating.",
  "who": 2
 },
 {
  "start": 3347.96,
  "end": 3351.96,
  "text": "We're in the middle of a revolution, a digital revolution. We don't quite know where it's going.",
  "who": 2
 },
 {
  "start": 3351.96,
  "end": 3355.96,
  "text": "We can do these extraordinary things now with gene editing.",
  "who": 2
 },
 {
  "start": 3355.96,
  "end": 3360.96,
  "text": "Do we have enough kind of moral, ethical capacities to control that?",
  "who": 2
 },
 {
  "start": 3360.96,
  "end": 3365.96,
  "text": "And it's science fiction that imagines both good versions and bad versions of what might come out of that.",
  "who": 2
 },
 {
  "start": 3365.96,
  "end": 3374.96,
  "text": "And understanding the history of science fiction and how it's shaped our understanding of reality in the past can help us make sense of where we might be going in the future.",
  "who": 1
 },
 {
  "start": 3375.52,
  "end": 3381.5199999999995,
  "text": "Yeah, definitely. I mean, and I think that's both, you know, both hard in the sense of technology and science,",
  "who": 2,
  "matched": true
 },
 {
  "start": 3381.5199999999995,
  "end": 3386.5199999999995,
  "text": "but also soft in the sense of what are the political consequences of this kind of thing?",
  "who": 2
 },
 {
  "start": 3386.5199999999995,
  "end": 3396.5199999999995,
  "text": "So, you know, The Handmaid's Tale by Margaret Atwood, written as an attack on conservative Reagan world in the 1980s,",
  "who": 2
 },
 {
  "start": 3396.5199999999995,
  "end": 3405.5199999999995,
  "text": "suddenly gets this major new boost, not just from shifting media, so becoming a TV streamed series,",
  "who": 2
 },
 {
  "start": 3405.5199999999995,
  "end": 3417.5199999999995,
  "text": "but also because of a political context in which abortion is suddenly shifted in the States and all of the protests pick up on the imaginary of Handmaid's Tale.",
  "who": 2
 },
 {
  "start": 3417.5199999999995,
  "end": 3421.5199999999995,
  "text": "So you get the handmaidens who arrive at protests and so on.",
  "who": 2
 },
 {
  "start": 3421.5199999999995,
  "end": 3428.5199999999995,
  "text": "So it's very powerful. And that kind of sense of she could see the kind of certain consequences of this.",
  "who": 2
 },
 {
  "start": 3428.5199999999995,
  "end": 3438.5199999999995,
  "text": "And isn't it freaky that a certain version of it has started to emerge, suggests the power of the imagination to project kind of forward and to warn,",
  "who": 2
 },
 {
  "start": 3438.5199999999995,
  "end": 3447.5199999999995,
  "text": "but also to embrace and celebrate as well as question or just say it's completely unpredictable what's going to happen.",
  "who": 2
 },
 {
  "start": 3447.5199999999995,
  "end": 3458.5199999999995,
  "text": "There's a great book by Charles Stross called Accelerando, which is about which is crazy because it's just a technological singularity happens.",
  "who": 2
 },
 {
  "start": 3458.5199999999995,
  "end": 3466.5199999999995,
  "text": "But then it's completely unpredictable, you know, and you can decide if you want to put your consciousness into a flock of birds for a while, if you like.",
  "who": 2
 },
 {
  "start": 3466.5199999999995,
  "end": 3471.5199999999995,
  "text": "And things get crazier and crazier and weirder and weirder because it's no longer in our control.",
  "who": 2
 },
 {
  "start": 3471.5199999999995,
  "end": 3476.5199999999995,
  "text": "You know, that's a sense of technology just producing itself and doing very weird and strange things.",
  "who": 2
 },
 {
  "start": 3476.5199999999995,
  "end": 3481.5199999999995,
  "text": "You know, there's lots of ways of imagining the future, which are really powerful still.",
  "who": 2
 },
 {
  "start": 3480.49,
  "end": 3487.49,
  "text": "That was Roger Luckhurst. The exhibition that Roger mentioned, Science Fiction Voyage to the Edge of Imagination,",
  "who": 0,
  "matched": true
 },
 {
  "start": 3487.96,
  "end": 3496.96,
  "text": "is running at the Science Museum in London until the 4th of May 2023. To find out more, visit sciencemuseum.org.uk.",
  "who": 0
 },
 {
  "start": 3496.96,
  "end": 3505.96,
  "text": "Thanks for listening to the History Extra podcast. This podcast was produced by Daniel Kramer Hardin.",
  "who": 0
 },
 {
  "start": 3526.96,
  "end": 3532.96,
  "text": "Rema 1000, always at low prices.",
  "who": 3
 }
]